{
  "message": "fix: regenerate architecture diagram without external references",
  "files": [
    {
      "sha": "e07627d0077a6cd016d0a08533ce48fd1781700c",
      "filename": "docs/src/content/docs/architecture.drawmode.ts",
      "status": "modified",
      "additions": 0,
      "deletions": 9,
      "changes": 9,
      "blob_url": "https://github.com/teamchong/zerobuf/blob/3acabce69d98abb112ac16ba0deb056202eee6ed/docs%2Fsrc%2Fcontent%2Fdocs%2Farchitecture.drawmode.ts",
      "raw_url": "https://github.com/teamchong/zerobuf/raw/3acabce69d98abb112ac16ba0deb056202eee6ed/docs%2Fsrc%2Fcontent%2Fdocs%2Farchitecture.drawmode.ts",
      "contents_url": "https://api.github.com/repos/teamchong/zerobuf/contents/docs%2Fsrc%2Fcontent%2Fdocs%2Farchitecture.drawmode.ts?ref=3acabce69d98abb112ac16ba0deb056202eee6ed",
      "patch": "@@ -1,7 +1,5 @@\n const d = new Diagram();\n \n-const databaseStyle = { color: \"database\", strokeWidth: 1, roughness: 0, opacity: 90, fontFamily: 2 };\n-\n const yourJstsCode = d.addBox(\"Your JS/TS Code\", { row: 0, col: 1, color: \"frontend\", width: 200, strokeWidth: 1, roughness: 0, opacity: 90, fontFamily: 2 });\n const zerobufcreateZerobufread = d.addBox(\"zerobuf.create()\\nzerobuf.read()\", { row: 1, col: 0, color: \"backend\", width: 200, strokeWidth: 1, roughness: 0, opacity: 90, fontFamily: 2 });\n const defineschemaSchemacreate = d.addBox(\"defineSchema()\\nschema.create()\", { row: 1, col: 2, color: \"backend\", width: 200, strokeWidth: 1, roughness: 0, opacity: 90, fontFamily: 2 });\n@@ -10,14 +8,10 @@ const arraybufferOrSharedarraybuffer = d.addBox(\"ArrayBuffer\\n(or SharedArrayBuf\n const worker = d.addBox(\"Worker\", { row: 4, col: 0, color: \"frontend\", width: 140, strokeWidth: 1, roughness: 0, opacity: 90, fontFamily: 2, icon: \"server\" });\n const wasmZigRustC = d.addBox(\"WASM\\n(Zig / Rust / C)\", { row: 4, col: 1, color: \"ai\", width: 160, strokeWidth: 1, roughness: 0, opacity: 90, fontFamily: 2 });\n const durableObject = d.addBox(\"Durable Object\", { row: 4, col: 2, color: \"backend\", width: 160, strokeWidth: 1, roughness: 0, opacity: 90, fontFamily: 2, icon: \"cloud\" });\n-const querymode = d.addBox(\"querymode\", { ...databaseStyle, row: 5, col: 0, width: 140 });\n-const gomode = d.addBox(\"gomode\", { ...databaseStyle, row: 5, col: 1, width: 140 });\n-const pymode = d.addBox(\"pymode\", { ...databaseStyle, row: 5, col: 2, width: 140 });\n \n const zerobufApi = d.addGroup(\"zerobuf API\", [zerobufcreateZerobufread, defineschemaSchemacreate], { padding: 20 });\n const memory = d.addGroup(\"Memory\", [arenaSaveRestoreAllocGrow, arraybufferOrSharedarraybuffer], { padding: 20 });\n const consumers = d.addGroup(\"Consumers\", [worker, wasmZigRustC, durableObject], { padding: 20 });\n-const downstream = d.addGroup(\"Downstream\", [querymode, gomode, pymode], { padding: 20 });\n \n d.connect(yourJstsCode, zerobufcreateZerobufread, \"dynamic\");\n d.connect(yourJstsCode, defineschemaSchemacreate, \"fixed layout\");\n@@ -27,8 +21,5 @@ d.connect(arenaSaveRestoreAllocGrow, arraybufferOrSharedarraybuffer, \"reads/writ\n d.connect(arraybufferOrSharedarraybuffer, worker, \"postMessage\\n(zero-copy)\");\n d.connect(arraybufferOrSharedarraybuffer, wasmZigRustC, \"memory.buffer\\n(shared)\");\n d.connect(arraybufferOrSharedarraybuffer, durableObject, \"storage.put\\n(binary)\");\n-d.connect(worker, querymode, undefined, { style: \"dashed\" });\n-d.connect(wasmZigRustC, gomode, undefined, { style: \"dashed\" });\n-d.connect(durableObject, pymode, undefined, { style: \"dashed\" });\n \n return d.render({ path: \"/Users/steven_chong/Downloads/repos/zerobuf/docs/src/content/docs/architecture\" });\n\\ No newline at end of file"
    },
    {
      "sha": "9af35f616de2b1b651249c5982faa54e36b3f188",
      "filename": "docs/src/content/docs/architecture.svg",
      "status": "modified",
      "additions": 2,
      "deletions": 2,
      "changes": 4,
      "blob_url": "https://github.com/teamchong/zerobuf/blob/3acabce69d98abb112ac16ba0deb056202eee6ed/docs%2Fsrc%2Fcontent%2Fdocs%2Farchitecture.svg",
      "raw_url": "https://github.com/teamchong/zerobuf/raw/3acabce69d98abb112ac16ba0deb056202eee6ed/docs%2Fsrc%2Fcontent%2Fdocs%2Farchitecture.svg",
      "contents_url": "https://api.github.com/repos/teamchong/zerobuf/contents/docs%2Fsrc%2Fcontent%2Fdocs%2Farchitecture.svg?ref=3acabce69d98abb112ac16ba0deb056202eee6ed",
      "patch": "@@ -1,4 +1,4 @@\n-<svg height=\"2124\" width=\"1904\" viewBox=\"0 0 952 1062\" xmlns=\"http://www.w3.org/2000/svg\" version=\"1.1\">\n+<svg height=\"1792\" width=\"1904\" viewBox=\"0 0 952 896\" xmlns=\"http://www.w3.org/2000/svg\" version=\"1.1\">\n   <!-- svg-source:excalidraw -->\n   \n   <defs>\n@@ -18,4 +18,4 @@\n     </style>\n     \n   </defs>\n-  <rect fill=\"#ffffff\" height=\"1062\" width=\"952\" y=\"0\" x=\"0\" /><g transform=\"translate(266 10) rotate(0 100 40)\" stroke-linecap=\"round\" fill-opacity=\"0.9\" stroke-opacity=\"0.9\"><path fill=\"#a5d8ff\" stroke-width=\"0\" stroke=\"none\" d=\"M20 0 C68.65 0, 117.31 0, 180 0 C193.33 0, 200 6.67, 200 20 C200 28.75, 200 37.51, 200 60 C200 73.33, 193.33 80, 180 80 C119.39 80, 58.78 80, 20 80 C6.67 80, 0 73.33, 0 60 C0 46.27, 0 32.54, 0 20 C0 6.67, 6.67 0, 20 0\" /><path fill=\"none\" stroke-width=\"1\" stroke=\"#1971c2\" d=\"M20 0 C67.56 0, 115.12 0, 180 0 M20 0 C83 0, 145.99 0, 180 0 M180 0 C193.33 0, 200 6.67, 200 20 M180 0 C193.33 0, 200 6.67, 200 20 M200 20 C200 30.39, 200 40.79, 200 60 M200 20 C200 35.97, 200 51.94, 200 60 M200 60 C200 73.33, 193.33 80, 180 80 M200 60 C200 73.33, 193.33 80, 180 80 M180 80 C132.34 80, 84.69 80, 20 80 M180 80 C133.24 80, 86.47 80, 20 80 M20 80 C6.67 80, 0 73.33, 0 60 M20 80 C6.67 80, 0 73.33, 0 60 M0 60 C0 47.02, 0 34.03, 0 20 M0 60 C0 44.13, 0 28.26, 0 20 M0 20 C0 6.67, 6.67 0, 20 0 M0 20 C0 6.67, 6.67 0, 20 0\" /></g><g transform=\"translate(276 40) rotate(0 90 10)\" fill-opacity=\"0.9\" stroke-opacity=\"0.9\"><text dominant-baseline=\"text-before-edge\" direction=\"ltr\" style=\"white-space: pre;\" text-anchor=\"middle\" fill=\"#1971c2\" font-size=\"16px\" font-family=\"Helvetica, Segoe UI Emoji\" y=\"0\" x=\"90\">Your JS/TS Code</text></g><g transform=\"translate(98 193) rotate(0 100 52)\" stroke-linecap=\"round\" fill-opacity=\"0.9\" stroke-opacity=\"0.9\"><path fill=\"#d0bfff\" stroke-width=\"0\" stroke=\"none\" d=\"M26 0 C56.89 0, 87.79 0, 174 0 C191.33 0, 200 8.67, 200 26 C200 44.98, 200 63.96, 200 78 C200 95.33, 191.33 104, 174 104 C121.63 104, 69.26 104, 26 104 C8.67 104, 0 95.33, 0 78 C0 60.53, 0 43.06, 0 26 C0 8.67, 8.67 0, 26 0\" /><path fill=\"none\" stroke-width=\"1\" stroke=\"#7048e8\" d=\"M26 0 C78.43 0, 130.87 0, 174 0 M26 0 C61.99 0, 97.98 0, 174 0 M174 0 C191.33 0, 200 8.67, 200 26 M174 0 C191.33 0, 200 8.67, 200 26 M200 26 C200 39.72, 200 53.44, 200 78 M200 26 C200 45.98, 200 65.96, 200 78 M200 78 C200 95.33, 191.33 104, 174 104 M200 78 C200 95.33, 191.33 104, 174 104 M174 104 C131.61 104, 89.22 104, 26 104 M174 104 C140.02 104, 106.04 104, 26 104 M26 104 C8.67 104, 0 95.33, 0 78 M26 104 C8.67 104, 0 95.33, 0 78 M0 78 C0 63.53, 0 49.06, 0 26 M0 78 C0 62.05, 0 46.1, 0 26 M0 26 C0 8.67, 8.67 0, 26 0 M0 26 C0 8.67, 8.67 0, 26 0\" /></g><g transform=\"translate(108 226.6) rotate(0 90 18.39999999999999)\" fill-opacity=\"0.9\" stroke-opacity=\"0.9\"><text dominant-baseline=\"text-before-edge\" direction=\"ltr\" style=\"white-space: pre;\" text-anchor=\"middle\" fill=\"#7048e8\" font-size=\"16px\" font-family=\"Helvetica, Segoe UI Emoji\" y=\"0\" x=\"90\">zerobuf.create()</text><text dominant-baseline=\"text-before-edge\" direction=\"ltr\" style=\"white-space: pre;\" text-anchor=\"middle\" fill=\"#7048e8\" font-size=\"16px\" font-family=\"Helvetica, Segoe UI Emoji\" y=\"18.4\" x=\"90\">zerobuf.read()</text></g><g transform=\"translate(514 193) rotate(0 100 52)\" stroke-linecap=\"round\" fill-opacity=\"0.9\" stroke-opacity=\"0.9\"><path fill=\"#d0bfff\" stroke-width=\"0\" stroke=\"none\" d=\"M26 0 C71.43 0, 116.85 0, 174 0 C191.33 0, 200 8.67, 200 26 C200 46.39, 200 66.79, 200 78 C200 95.33, 191.33 104, 174 104 C126.76 104, 79.53 104, 26 104 C8.67 104, 0 95.33, 0 78 C0 61.42, 0 44.84, 0 26 C0 8.67, 8.67 0, 26 0\" /><path fill=\"none\" stroke-width=\"1\" stroke=\"#7048e8\" d=\"M26 0 C78.96 0, 131.92 0, 174 0 M26 0 C72.31 0, 118.62 0, 174 0 M174 0 C191.33 0, 200 8.67, 200 26 M174 0 C191.33 0, 200 8.67, 200 26 M200 26 C200 42.77, 200 59.55, 200 78 M200 26 C200 39.25, 200 52.49, 200 78 M200 78 C200 95.33, 191.33 104, 174 104 M200 78 C200 95.33, 191.33 104, 174 104 M174 104 C134.68 104, 95.36 104, 26 104 M174 104 C127.99 104, 81.99 104, 26 104 M26 104 C8.67 104, 0 95.33, 0 78 M26 104 C8.67 104, 0 95.33, 0 78 M0 78 C0 59.35, 0 40.7, 0 26 M0 78 C0 65.96, 0 53.93, 0 26 M0 26 C0 8.67, 8.67 0, 26 0 M0 26 C0 8.67, 8.67 0, 26 0\" /></g><g transform=\"translate(524 226.6) rotate(0 90 18.39999999999999)\" fill-opacity=\"0.9\" stroke-opacity=\"0.9\"><text dominant-baseline=\"text-before-edge\" direction=\"ltr\" style=\"white-space: pre;\" text-anchor=\"middle\" fill=\"#7048e8\" font-size=\"16px\" font-family=\"Helvetica, Segoe UI Emoji\" y=\"0\" x=\"90\">defineSchema()</text><text dominant-baseline=\"text-before-edge\" direction=\"ltr\" style=\"white-space: pre;\" text-anchor=\"middle\" fill=\"#7048e8\" font-size=\"16px\" font-family=\"Helvetica, Segoe UI Emoji\" y=\"18.4\" x=\"90\">schema.create()</text></g><g transform=\"translate(236 400) rotate(0 130 40)\" stroke-linecap=\"round\" fill-opacity=\"0.9\" stroke-opacity=\"0.9\"><path fill=\"#ffa8a8\" stroke-width=\"0\" stroke=\"none\" d=\"M20 0 C105.67 0, 191.33 0, 240 0 C253.33 0, 260 6.67, 260 20 C260 30.78, 260 41.56, 260 60 C260 73.33, 253.33 80, 240 80 C153.54 80, 67.07 80, 20 80 C6.67 80, 0 73.33, 0 60 C0 49.95, 0 39.91, 0 20 C0 6.67, 6.67 0, 20 0\" /><path fill=\"none\" stroke-width=\"1\" stroke=\"#c92a2a\" d=\"M20 0 C66.84 0, 113.69 0, 240 0 M20 0 C93.95 0, 167.89 0, 240 0 M240 0 C253.33 0, 260 6.67, 260 20 M240 0 C253.33 0, 260 6.67, 260 20 M260 20 C260 34.72, 260 49.43, 260 60 M260 20 C260 34.05, 260 48.1, 260 60 M260 60 C260 73.33, 253.33 80, 240 80 M260 60 C260 73.33, 253.33 80, 240 80 M240 80 C181.48 80, 122.95 80, 20 80 M240 80 C170.69 80, 101.39 80, 20 80 M20 80 C6.67 80, 0 73.33, 0 60 M20 80 C6.67 80, 0 73.33, 0 60 M0 60 C0 46.74, 0 33.48, 0 20 M0 60 C0 49.38, 0 38.76, 0 20 M0 20 C0 6.67, 6.67 0, 20 0 M0 20 C0 6.67, 6.67 0, 20 0\" /></g><g transform=\"translate(246 412.4) rotate(0 120 27.599999999999994)\" fill-opacity=\"0.9\" stroke-opacity=\"0.9\"><text dominant-baseline=\"text-before-edge\" direction=\"ltr\" style=\"white-space: pre;\" text-anchor=\"middle\" fill=\"#c92a2a\" font-size=\"16px\" font-family=\"Helvetica, Segoe UI Emoji\" y=\"0\" x=\"120\">Arena</text><text dominant-baseline=\"text-before-edge\" direction=\"ltr\" style=\"white-space: pre;\" text-anchor=\"middle\" fill=\"#c92a2a\" font-size=\"16px\" font-family=\"Helvetica, Segoe UI Emoji\" y=\"18.4\" x=\"120\">save() / restore()</text><text dominant-baseline=\"text-before-edge\" direction=\"ltr\" style=\"white-space: pre;\" text-anchor=\"middle\" fill=\"#c92a2a\" font-size=\"16px\" font-family=\"Helvetica, Segoe UI Emoji\" y=\"36.8\" x=\"120\">alloc() / grow()</text></g><g transform=\"translate(236 582) rotate(0 130 30)\" stroke-linecap=\"round\" fill-opacity=\"0.9\" stroke-opacity=\"0.9\"><path fill=\"#ffec99\" stroke-width=\"0\" stroke=\"none\" d=\"M15 0 C62.08 0, 109.16 0, 245 0 C255 0, 260 5, 260 15 C260 22.44, 260 29.88, 260 45 C260 55, 255 60, 245 60 C175.85 60, 106.7 60, 15 60 C5 60, 0 55, 0 45 C0 36.99, 0 28.98, 0 15 C0 5, 5 0, 15 0\" /><path fill=\"none\" stroke-width=\"1\" stroke=\"#f08c00\" d=\"M15 0 C84.98 0, 154.96 0, 245 0 M15 0 C106.02 0, 197.03 0, 245 0 M245 0 C255 0, 260 5, 260 15 M245 0 C255 0, 260 5, 260 15 M260 15 C260 26.88, 260 38.76, 260 45 M260 15 C260 26, 260 37.01, 260 45 M260 45 C260 55, 255 60, 245 60 M260 45 C260 55, 255 60, 245 60 M245 60 C164.39 60, 83.77 60, 15 60 M245 60 C153.9 60, 62.81 60, 15 60 M15 60 C5 60, 0 55, 0 45 M15 60 C5 60, 0 55, 0 45 M0 45 C0 36.85, 0 28.7, 0 15 M0 45 C0 35.46, 0 25.93, 0 15 M0 15 C0 5, 5 0, 15 0 M0 15 C0 5, 5 0, 15 0\" /></g><g transform=\"translate(246 593.6) rotate(0 120 18.399999999999977)\" fill-opacity=\"0.9\" stroke-opacity=\"0.9\"><text dominant-baseline=\"text-before-edge\" direction=\"ltr\" style=\"white-space: pre;\" text-anchor=\"middle\" fill=\"#f08c00\" font-size=\"16px\" font-family=\"Helvetica, Segoe UI Emoji\" y=\"0\" x=\"120\">ArrayBuffer</text><text dominant-baseline=\"text-before-edge\" direction=\"ltr\" style=\"white-space: pre;\" text-anchor=\"middle\" fill=\"#f08c00\" font-size=\"16px\" font-family=\"Helvetica, Segoe UI Emoji\" y=\"18.4\" x=\"120\">(or SharedArrayBuffer)</text></g><g transform=\"translate(30 762) rotate(0 70 52)\" stroke-linecap=\"round\" fill-opacity=\"0.9\" stroke-opacity=\"0.9\"><path fill=\"#a5d8ff\" stroke-width=\"0\" stroke=\"none\" d=\"M26 0 C49.88 0, 73.77 0, 114 0 C131.33 0, 140 8.67, 140 26 C140 44.8, 140 63.6, 140 78 C140 95.33, 131.33 104, 114 104 C94.98 104, 75.96 104, 26 104 C8.67 104, 0 95.33, 0 78 C0 57.45, 0 36.91, 0 26 C0 8.67, 8.67 0, 26 0\" /><path fill=\"none\" stroke-width=\"1\" stroke=\"#1971c2\" d=\"M26 0 C46.94 0, 67.88 0, 114 0 M26 0 C46.23 0, 66.47 0, 114 0 M114 0 C131.33 0, 140 8.67, 140 26 M114 0 C131.33 0, 140 8.67, 140 26 M140 26 C140 42.82, 140 59.64, 140 78 M140 26 C140 46.32, 140 66.65, 140 78 M140 78 C140 95.33, 131.33 104, 114 104 M140 78 C140 95.33, 131.33 104, 114 104 M114 104 C93.51 104, 73.02 104, 26 104 M114 104 C89.79 104, 65.57 104, 26 104 M26 104 C8.67 104, 0 95.33, 0 78 M26 104 C8.67 104, 0 95.33, 0 78 M0 78 C0 62.65, 0 47.3, 0 26 M0 78 C0 59.24, 0 40.49, 0 26 M0 26 C0 8.67, 8.67 0, 26 0 M0 26 C0 8.67, 8.67 0, 26 0\" /></g><g transform=\"translate(40 795.6) rotate(0 60 18.399999999999977)\" fill-opacity=\"0.9\" stroke-opacity=\"0.9\"><text dominant-baseline=\"text-before-edge\" direction=\"ltr\" style=\"white-space: pre;\" text-anchor=\"middle\" fill=\"#1971c2\" font-size=\"16px\" font-family=\"Helvetica, Segoe UI Emoji\" y=\"0\" x=\"60\">\ud83d\udda5\ufe0f</text><text dominant-baseline=\"text-before-edge\" direction=\"ltr\" style=\"white-space: pre;\" text-anchor=\"middle\" fill=\"#1971c2\" font-size=\"16px\" font-family=\"Helvetica, Segoe UI Emoji\" y=\"18.4\" x=\"60\">Worker</text></g><g transform=\"translate(387 762) rotate(0 80 52)\" stroke-linecap=\"round\" fill-opacity=\"0.9\" stroke-opacity=\"0.9\"><path fill=\"#e599f7\" stroke-width=\"0\" stroke=\"none\" d=\"M26 0 C59.11 0, 92.22 0, 134 0 C151.33 0, 160 8.67, 160 26 C160 42.27, 160 58.55, 160 78 C160 95.33, 151.33 104, 134 104 C107.34 104, 80.68 104, 26 104 C8.67 104, 0 95.33, 0 78 C0 64.51, 0 51.03, 0 26 C0 8.67, 8.67 0, 26 0\" /><path fill=\"none\" stroke-width=\"1\" stroke=\"#9c36b5\" d=\"M26 0 C50.18 0, 74.35 0, 134 0 M26 0 C64.7 0, 103.41 0, 134 0 M134 0 C151.33 0, 160 8.67, 160 26 M134 0 C151.33 0, 160 8.67, 160 26 M160 26 C160 44.04, 160 62.09, 160 78 M160 26 C160 43.26, 160 60.53, 160 78 M160 78 C160 95.33, 151.33 104, 134 104 M160 78 C160 95.33, 151.33 104, 134 104 M134 104 C91.08 104, 48.15 104, 26 104 M134 104 C105.03 104, 76.06 104, 26 104 M26 104 C8.67 104, 0 95.33, 0 78 M26 104 C8.67 104, 0 95.33, 0 78 M0 78 C0 65.15, 0 52.3, 0 26 M0 78 C0 63.5, 0 49.01, 0 26 M0 26 C0 8.67, 8.67 0, 26 0 M0 26 C0 8.67, 8.67 0, 26 0\" /></g><g transform=\"translate(397 795.6) rotate(0 70 18.399999999999977)\" fill-opacity=\"0.9\" stroke-opacity=\"0.9\"><text dominant-baseline=\"text-before-edge\" direction=\"ltr\" style=\"white-space: pre;\" text-anchor=\"middle\" fill=\"#9c36b5\" font-size=\"16px\" font-family=\"Helvetica, Segoe UI Emoji\" y=\"0\" x=\"70\">WASM</text><text dominant-baseline=\"text-before-edge\" direction=\"ltr\" style=\"white-space: pre;\" text-anchor=\"middle\" fill=\"#9c36b5\" font-size=\"16px\" font-family=\"Helvetica, Segoe UI Emoji\" y=\"18.4\" x=\"70\">(Zig / Rust / C)</text></g><g transform=\"translate(762 762) rotate(0 80 52)\" stroke-linecap=\"round\" fill-opacity=\"0.9\" stroke-opacity=\"0.9\"><path fill=\"#d0bfff\" stroke-width=\"0\" stroke=\"none\" d=\"M26 0 C53 0, 80 0, 134 0 C151.33 0, 160 8.67, 160 26 C160 39.88, 160 53.76, 160 78 C160 95.33, 151.33 104, 134 104 C95.3 104, 56.6 104, 26 104 C8.67 104, 0 95.33, 0 78 C0 61.03, 0 44.05, 0 26 C0 8.67, 8.67 0, 26 0\" /><path fill=\"none\" stroke-width=\"1\" stroke=\"#7048e8\" d=\"M26 0 C68.26 0, 110.52 0, 134 0 M26 0 C55.34 0, 84.68 0, 134 0 M134 0 C151.33 0, 160 8.67, 160 26 M134 0 C151.33 0, 160 8.67, 160 26 M160 26 C160 43.85, 160 61.71, 160 78 M160 26 C160 40.65, 160 55.29, 160 78 M160 78 C160 95.33, 151.33 104, 134 104 M160 78 C160 95.33, 151.33 104, 134 104 M134 104 C94.71 104, 55.41 104, 26 104 M134 104 C104.3 104, 74.6 104, 26 104 M26 104 C8.67 104, 0 95.33, 0 78 M26 104 C8.67 104, 0 95.33, 0 78 M0 78 C0 62.39, 0 46.78, 0 26 M0 78 C0 65.69, 0 53.38, 0 26 M0 26 C0 8.67, 8.67 0, 26 0 M0 26 C0 8.67, 8.67 0, 26 0\" /></g><g transform=\"translate(772 795.6) rotate(0 70 18.399999999999977)\" fill-opacity=\"0.9\" stroke-opacity=\"0.9\"><text dominant-baseline=\"text-before-edge\" direction=\"ltr\" style=\"white-space: pre;\" text-anchor=\"middle\" fill=\"#7048e8\" font-size=\"16px\" font-family=\"Helvetica, Segoe UI Emoji\" y=\"0\" x=\"70\">\u2601\ufe0f</text><text dominant-baseline=\"text-before-edge\" direction=\"ltr\" style=\"white-space: pre;\" text-anchor=\"middle\" fill=\"#7048e8\" font-size=\"16px\" font-family=\"Helvetica, Segoe UI Emoji\" y=\"18.4\" x=\"70\">Durable Object</text></g><g transform=\"translate(30 952) rotate(0 70 40)\" stroke-linecap=\"round\" fill-opacity=\"0.9\" stroke-opacity=\"0.9\"><path fill=\"#b2f2bb\" stroke-width=\"0\" stroke=\"none\" d=\"M20 0 C43.55 0, 67.11 0, 120 0 C133.33 0, 140 6.67, 140 20 C140 35.67, 140 51.34, 140 60 C140 73.33, 133.33 80, 120 80 C84.19 80, 48.38 80, 20 80 C6.67 80, 0 73.33, 0 60 C0 51.6, 0 43.19, 0 20 C0 6.67, 6.67 0, 20 0\" /><path fill=\"none\" stroke-width=\"1\" stroke=\"#2f9e44\" d=\"M20 0 C51.33 0, 82.66 0, 120 0 M20 0 C51.47 0, 82.94 0, 120 0 M120 0 C133.33 0, 140 6.67, 140 20 M120 0 C133.33 0, 140 6.67, 140 20 M140 20 C140 35.5, 140 50.99, 140 60 M140 20 C140 30.02, 140 40.05, 140 60 M140 60 C140 73.33, 133.33 80, 120 80 M140 60 C140 73.33, 133.33 80, 120 80 M120 80 C99.35 80, 78.69 80, 20 80 M120 80 C98.46 80, 76.92 80, 20 80 M20 80 C6.67 80, 0 73.33, 0 60 M20 80 C6.67 80, 0 73.33, 0 60 M0 60 C0 51.82, 0 43.63, 0 20 M0 60 C0 50.36, 0 40.73, 0 20 M0 20 C0 6.67, 6.67 0, 20 0 M0 20 C0 6.67, 6.67 0, 20 0\" /></g><g transform=\"translate(40 982) rotate(0 60 10)\" fill-opacity=\"0.9\" stroke-opacity=\"0.9\"><text dominant-baseline=\"text-before-edge\" direction=\"ltr\" style=\"white-space: pre;\" text-anchor=\"middle\" fill=\"#2f9e44\" font-size=\"16px\" font-family=\"Helvetica, Segoe UI Emoji\" y=\"0\" x=\"60\">querymode</text></g><g transform=\"translate(397 952) rotate(0 70 40)\" stroke-linecap=\"round\" fill-opacity=\"0.9\" stroke-opacity=\"0.9\"><path fill=\"#b2f2bb\" stroke-width=\"0\" stroke=\"none\" d=\"M20 0 C54.75 0, 89.5 0, 120 0 C133.33 0, 140 6.67, 140 20 C140 34.96, 140 49.92, 140 60 C140 73.33, 133.33 80, 120 80 C95.33 80, 70.65 80, 20 80 C6.67 80, 0 73.33, 0 60 C0 49.43, 0 38.86, 0 20 C0 6.67, 6.67 0, 20 0\" /><path fill=\"none\" stroke-width=\"1\" stroke=\"#2f9e44\" d=\"M20 0 C48.89 0, 77.77 0, 120 0 M20 0 C44.5 0, 69 0, 120 0 M120 0 C133.33 0, 140 6.67, 140 20 M120 0 C133.33 0, 140 6.67, 140 20 M140 20 C140 29.26, 140 38.53, 140 60 M140 20 C140 33.76, 140 47.52, 140 60 M140 60 C140 73.33, 133.33 80, 120 80 M140 60 C140 73.33, 133.33 80, 120 80 M120 80 C98.3 80, 76.6 80, 20 80 M120 80 C97.46 80, 74.91 80, 20 80 M20 80 C6.67 80, 0 73.33, 0 60 M20 80 C6.67 80, 0 73.33, 0 60 M0 60 C0 52, 0 43.99, 0 20 M0 60 C0 44.78, 0 29.56, 0 20 M0 20 C0 6.67, 6.67 0, 20 0 M0 20 C0 6.67, 6.67 0, 20 0\" /></g><g transform=\"translate(407 982) rotate(0 60 10)\" fill-opacity=\"0.9\" stroke-opacity=\"0.9\"><text dominant-baseline=\"text-before-edge\" direction=\"ltr\" style=\"white-space: pre;\" text-anchor=\"middle\" fill=\"#2f9e44\" font-size=\"16px\" font-family=\"Helvetica, Segoe UI Emoji\" y=\"0\" x=\"60\">gomode</text></g><g transform=\"translate(772 952) rotate(0 70 40)\" stroke-linecap=\"round\" fill-opacity=\"0.9\" stroke-opacity=\"0.9\"><path fill=\"#b2f2bb\" stroke-width=\"0\" stroke=\"none\" d=\"M20 0 C41.3 0, 62.61 0, 120 0 C133.33 0, 140 6.67, 140 20 C140 35.66, 140 51.31, 140 60 C140 73.33, 133.33 80, 120 80 C96.32 80, 72.64 80, 20 80 C6.67 80, 0 73.33, 0 60 C0 46.63, 0 33.25, 0 20 C0 6.67, 6.67 0, 20 0\" /><path fill=\"none\" stroke-width=\"1\" stroke=\"#2f9e44\" d=\"M20 0 C58.56 0, 97.12 0, 120 0 M20 0 C43.18 0, 66.35 0, 120 0 M120 0 C133.33 0, 140 6.67, 140 20 M120 0 C133.33 0, 140 6.67, 140 20 M140 20 C140 34.57, 140 49.15, 140 60 M140 20 C140 34.73, 140 49.46, 140 60 M140 60 C140 73.33, 133.33 80, 120 80 M140 60 C140 73.33, 133.33 80, 120 80 M120 80 C80.83 80, 41.65 80, 20 80 M120 80 C80.23 80, 40.46 80, 20 80 M20 80 C6.67 80, 0 73.33, 0 60 M20 80 C6.67 80, 0 73.33, 0 60 M0 60 C0 49.55, 0 39.1, 0 20 M0 60 C0 49.42, 0 38.84, 0 20 M0 20 C0 6.67, 6.67 0, 20 0 M0 20 C0 6.67, 6.67 0, 20 0\" /></g><g transform=\"translate(782 982) rotate(0 60 10)\" fill-opacity=\"0.9\" stroke-opacity=\"0.9\"><text dominant-baseline=\"text-before-edge\" direction=\"ltr\" style=\"white-space: pre;\" text-anchor=\"middle\" fill=\"#2f9e44\" font-size=\"16px\" font-family=\"Helvetica, Segoe UI Emoji\" y=\"0\" x=\"60\">pymode</text></g><g stroke-linecap=\"round\"><g transform=\"translate(334 89) rotate(0 -44 50)\"><path fill=\"none\" stroke-width=\"2\" stroke=\"#7048e8\" d=\"M0 0 C-22.46 25.52, -44.92 51.05, -88 100 M0 0 C-34.59 39.3, -69.17 78.6, -88 100\" /></g><g transform=\"translate(334 89) rotate(0 -44 50)\"><path fill=\"none\" stroke-width=\"2\" stroke=\"#7048e8\" d=\"M-77.08 72.06 C-79.87 79.19, -82.65 86.32, -88 100 M-77.08 72.06 C-81.37 83.04, -85.66 94.02, -88 100\" /></g><g transform=\"translate(334 89) rotate(0 -44 50)\"><path fill=\"none\" stroke-width=\"2\" stroke=\"#7048e8\" d=\"M-61.67 85.62 C-68.39 89.29, -75.11 92.96, -88 100 M-61.67 85.62 C-72.02 91.27, -82.37 96.92, -88 100\" /></g></g><mask /><g transform=\"translate(284.6 130) rotate(0 37.39999999999999 10)\"><text dominant-baseline=\"text-before-edge\" direction=\"ltr\" style=\"white-space: pre;\" text-anchor=\"middle\" fill=\"#1e1e1e\" font-size=\"14px\" font-family=\"Virgil, Segoe UI Emoji\" y=\"0\" x=\"37.400000000000006\">dynamic</text></g><g stroke-linecap=\"round\"><g transform=\"translate(376 87) rotate(0 87 53.5)\"><path fill=\"none\" stroke-width=\"2\" stroke=\"#7048e8\" d=\"M0 0 C68.83 42.33, 137.66 84.65, 174 107 M0 0 C42.85 26.35, 85.71 52.7, 174 107\" /></g><g transform=\"translate(376 87) rotate(0 87 53.5)\"><path fill=\"none\" stroke-width=\"2\" stroke=\"#7048e8\" d=\"M144.61 100.97 C156.24 103.36, 167.86 105.74, 174 107 M144.61 100.97 C151.85 102.46, 159.09 103.94, 174 107\" /></g><g transform=\"translate(376 87) rotate(0 87 53.5)\"><path fill=\"none\" stroke-width=\"2\" stroke=\"#7048e8\" d=\"M155.36 83.49 C162.73 92.79, 170.11 102.09, 174 107 M155.36 83.49 C159.95 89.28, 164.54 95.07, 174 107\" /></g></g><mask /><g transform=\"translate(482.6 130) rotate(0 58.400000000000034 10)\"><text dominant-baseline=\"text-before-edge\" direction=\"ltr\" style=\"white-space: pre;\" text-anchor=\"middle\" fill=\"#1e1e1e\" font-size=\"14px\" font-family=\"Virgil, Segoe UI Emoji\" y=\"0\" x=\"58.400000000000006\">fixed layout</text></g><g stroke-linecap=\"round\"><g transform=\"translate(239 293) rotate(0 43.5 49.5)\"><path fill=\"none\" stroke-width=\"2\" stroke=\"#c92a2a\" d=\"M0 0 C32.58 37.08, 65.17 74.16, 87 99 M0 0 C33.59 38.23, 67.19 76.45, 87 99\" /></g><g transform=\"translate(239 293) rotate(0 43.5 49.5)\"><path fill=\"none\" stroke-width=\"2\" stroke=\"#c92a2a\" d=\"M60.68 84.6 C70.54 89.99, 80.4 95.39, 87 99 M60.68 84.6 C70.85 90.16, 81.01 95.72, 87 99\" /></g><g transform=\"translate(239 293) rotate(0 43.5 49.5)\"><path fill=\"none\" stroke-width=\"2\" stroke=\"#c92a2a\" d=\"M76.1 71.05 C80.18 81.52, 84.26 91.99, 87 99 M76.1 71.05 C80.31 81.84, 84.52 92.63, 87 99\" /></g></g><mask /><g transform=\"translate(284.4 336) rotate(0 62.60000000000001 10)\"><text dominant-baseline=\"text-before-edge\" direction=\"ltr\" style=\"white-space: pre;\" text-anchor=\"middle\" fill=\"#1e1e1e\" font-size=\"14px\" font-family=\"Virgil, Segoe UI Emoji\" y=\"0\" x=\"62.6\">encode/decode</text></g><g stroke-linecap=\"round\"><g transform=\"translate(559 289) rotate(0 -68.5 53)\"><path fill=\"none\" stroke-width=\"2\" stroke=\"#c92a2a\" d=\"M0 0 C-44.17 34.17, -88.34 68.35, -137 106 M0 0 C-31.13 24.08, -62.26 48.17, -137 106\" /></g><g transform=\"translate(559 289) rotate(0 -68.5 53)\"><path fill=\"none\" stroke-width=\"2\" stroke=\"#c92a2a\" d=\"M-120.98 80.63 C-126.15 88.81, -131.31 96.99, -137 106 M-120.98 80.63 C-124.62 86.4, -128.26 92.16, -137 106\" /></g><g transform=\"translate(559 289) rotate(0 -68.5 53)\"><path fill=\"none\" stroke-width=\"2\" stroke=\"#c92a2a\" d=\"M-108.42 96.86 C-117.64 99.81, -126.85 102.75, -137 106 M-108.42 96.86 C-114.92 98.94, -121.41 101.02, -137 106\" /></g></g><mask /><g transform=\"translate(482.2 336) rotate(0 87.79999999999998 10)\"><text dominant-baseline=\"text-before-edge\" direction=\"ltr\" style=\"white-space: pre;\" text-anchor=\"middle\" fill=\"#1e1e1e\" font-size=\"14px\" font-family=\"Virgil, Segoe UI Emoji\" y=\"0\" x=\"87.8\">precomputed offsets</text></g><g stroke-linecap=\"round\"><g transform=\"translate(366 480) rotate(0 0 45.5)\"><path fill=\"none\" stroke-width=\"2\" stroke=\"#f08c00\" d=\"M0 0 C0 30.38, 0 60.76, 0 91 M0 0 C0 32.28, 0 64.57, 0 91\" /></g><g transform=\"translate(366 480) rotate(0 0 45.5)\"><path fill=\"none\" stroke-width=\"2\" stroke=\"#f08c00\" d=\"M-10.26 62.81 C-6.84 72.22, -3.41 81.63, 0 91 M-10.26 62.81 C-6.62 72.81, -2.98 82.81, 0 91\" /></g><g transform=\"translate(366 480) rotate(0 0 45.5)\"><path fill=\"none\" stroke-width=\"2\" stroke=\"#f08c00\" d=\"M10.26 62.81 C6.84 72.22, 3.41 81.63, 0 91 M10.26 62.81 C6.62 72.81, 2.98 82.81, 0 91\" /></g></g><mask /><g transform=\"translate(358.6 519) rotate(0 58.400000000000006 10)\"><text dominant-baseline=\"text-before-edge\" direction=\"ltr\" style=\"white-space: pre;\" text-anchor=\"middle\" fill=\"#1e1e1e\" font-size=\"14px\" font-family=\"Virgil, Segoe UI Emoji\" y=\"0\" x=\"58.400000000000006\">reads/writes</text></g><g stroke-linecap=\"round\"><g transform=\"translate(329 641) rotate(0 -85.5 64)\"><path fill=\"none\" stroke-width=\"2\" stroke=\"#1971c2\" d=\"M0 0 C-42.05 31.48, -84.1 62.96, -171 128 M0 0 C-57.86 43.31, -115.72 86.62, -171 128\" /></g><g transform=\"translate(329 641) rotate(0 -85.5 64)\"><path fill=\"none\" stroke-width=\"2\" stroke=\"#1971c2\" d=\"M-154.58 102.89 C-158.62 109.07, -162.66 115.24, -171 128 M-154.58 102.89 C-160.14 111.39, -165.69 119.88, -171 128\" /></g><g transform=\"translate(329 641) rotate(0 -85.5 64)\"><path fill=\"none\" stroke-width=\"2\" stroke=\"#1971c2\" d=\"M-142.28 119.32 C-149.34 121.46, -156.41 123.59, -171 128 M-142.28 119.32 C-152 122.26, -161.72 125.19, -171 128\" /></g></g><mask /><g transform=\"translate(198.60000000000002 658) rotate(0 54.19999999999999 10)\"><text dominant-baseline=\"text-before-edge\" direction=\"ltr\" style=\"white-space: pre;\" text-anchor=\"middle\" fill=\"#1e1e1e\" font-size=\"14px\" font-family=\"Virgil, Segoe UI Emoji\" y=\"0\" x=\"54.2\">postMessage</text><text dominant-baseline=\"text-before-edge\" direction=\"ltr\" style=\"white-space: pre;\" text-anchor=\"middle\" fill=\"#1e1e1e\" font-size=\"14px\" font-family=\"Virgil, Segoe UI Emoji\" y=\"17.5\" x=\"54.2\">(zero-copy)</text></g><g stroke-linecap=\"round\"><g transform=\"translate(334 642) rotate(0 52 56)\"><path fill=\"none\" stroke-width=\"2\" stroke=\"#9c36b5\" d=\"M0 0 C33.37 35.93, 66.73 71.86, 104 112 M0 0 C30.75 33.12, 61.51 66.24, 104 112\" /></g><g transform=\"translate(334 642) rotate(0 52 56)\"><path fill=\"none\" stroke-width=\"2\" stroke=\"#9c36b5\" d=\"M77.3 98.32 C85.86 102.71, 94.43 107.1, 104 112 M77.3 98.32 C85.19 102.37, 93.09 106.41, 104 112\" /></g><g transform=\"translate(334 642) rotate(0 52 56)\"><path fill=\"none\" stroke-width=\"2\" stroke=\"#9c36b5\" d=\"M92.34 84.36 C96.08 93.23, 99.82 102.1, 104 112 M92.34 84.36 C95.79 92.53, 99.23 100.71, 104 112\" /></g></g><mask /><g transform=\"translate(408.4 722) rotate(0 62.599999999999994 10)\"><text dominant-baseline=\"text-before-edge\" direction=\"ltr\" style=\"white-space: pre;\" text-anchor=\"middle\" fill=\"#1e1e1e\" font-size=\"14px\" font-family=\"Virgil, Segoe UI Emoji\" y=\"0\" x=\"62.6\">memory.buffer</text><text dominant-baseline=\"text-before-edge\" direction=\"ltr\" style=\"white-space: pre;\" text-anchor=\"middle\" fill=\"#1e1e1e\" font-size=\"14px\" font-family=\"Virgil, Segoe UI Emoji\" y=\"17.5\" x=\"62.6\">(shared)</text></g><g stroke-linecap=\"round\"><g transform=\"translate(479 639) rotate(0 143.5 70)\"><path fill=\"none\" stroke-width=\"2\" stroke=\"#7048e8\" d=\"M0 0 C20.5 12.74, 41 25.49, 74 46 M0 0 C24.97 15.52, 49.94 31.04, 74 46 M74 46 C135.83 73.29, 197.67 100.58, 287 140 M74 46 C149.16 79.17, 224.32 112.34, 287 140\" /></g><g transform=\"translate(479 639) rotate(0 143.5 70)\"><path fill=\"none\" stroke-width=\"2\" stroke=\"#7048e8\" d=\"M257.07 138.01 C265.36 138.56, 273.65 139.11, 287 140 M257.07 138.01 C267.17 138.68, 277.27 139.35, 287 140\" /></g><g transform=\"translate(479 639) rotate(0 143.5 70)\"><path fill=\"none\" stroke-width=\"2\" stroke=\"#7048e8\" d=\"M265.35 119.23 C271.35 124.98, 277.35 130.74, 287 140 M265.35 119.23 C272.66 126.24, 279.96 133.25, 287 140\" /></g></g><mask /><g transform=\"translate(614.8 672) rotate(0 54.19999999999999 10)\"><text dominant-baseline=\"text-before-edge\" direction=\"ltr\" style=\"white-space: pre;\" text-anchor=\"middle\" fill=\"#1e1e1e\" font-size=\"14px\" font-family=\"Virgil, Segoe UI Emoji\" y=\"0\" x=\"54.2\">storage.put</text><text dominant-baseline=\"text-before-edge\" direction=\"ltr\" style=\"white-space: pre;\" text-anchor=\"middle\" fill=\"#1e1e1e\" font-size=\"14px\" font-family=\"Virgil, Segoe UI Emoji\" y=\"17.5\" x=\"54.2\">(binary)</text></g><g stroke-linecap=\"round\"><g transform=\"translate(136 858) rotate(0 0 44)\"><path stroke-dasharray=\"8 10\" fill=\"none\" stroke-width=\"2.5\" stroke=\"#2f9e44\" d=\"M0 0 C0 19.92, 0 39.85, 0 88\" /></g><g transform=\"translate(136 858) rotate(0 0 44)\"><path fill=\"none\" stroke-width=\"2.5\" stroke=\"#2f9e44\" d=\"M-10.26 59.81 C-7.94 66.19, -5.61 72.57, 0 88\" /></g><g transform=\"translate(136 858) rotate(0 0 44)\"><path fill=\"none\" stroke-width=\"2.5\" stroke=\"#2f9e44\" d=\"M10.26 59.81 C7.94 66.19, 5.61 72.57, 0 88\" /></g></g><mask /><g stroke-linecap=\"round\"><g transform=\"translate(467 866) rotate(0 0 37.5)\"><path stroke-dasharray=\"8 10\" fill=\"none\" stroke-width=\"2.5\" stroke=\"#2f9e44\" d=\"M0 0 C0 23.78, 0 47.56, 0 75\" /></g><g transform=\"translate(467 866) rotate(0 0 37.5)\"><path fill=\"none\" stroke-width=\"2.5\" stroke=\"#2f9e44\" d=\"M-10.26 46.81 C-7.01 55.75, -3.75 64.68, 0 75\" /></g><g transform=\"translate(467 866) rotate(0 0 37.5)\"><path fill=\"none\" stroke-width=\"2.5\" stroke=\"#2f9e44\" d=\"M10.26 46.81 C7.01 55.75, 3.75 64.68, 0 75\" /></g></g><mask /><g stroke-linecap=\"round\"><g transform=\"translate(842 866) rotate(0 0 37.5)\"><path stroke-dasharray=\"8 10\" fill=\"none\" stroke-width=\"2.5\" stroke=\"#2f9e44\" d=\"M0 0 C0 27.32, 0 54.65, 0 75\" /></g><g transform=\"translate(842 866) rotate(0 0 37.5)\"><path fill=\"none\" stroke-width=\"2.5\" stroke=\"#2f9e44\" d=\"M-10.26 46.81 C-6.52 57.08, -2.78 67.35, 0 75\" /></g><g transform=\"translate(842 866) rotate(0 0 37.5)\"><path fill=\"none\" stroke-width=\"2.5\" stroke=\"#2f9e44\" d=\"M10.26 46.81 C6.52 57.08, 2.78 67.35, 0 75\" /></g></g><mask /><g transform=\"translate(78 153) rotate(0 328 82)\" stroke-linecap=\"round\" fill-opacity=\"0.6\" stroke-opacity=\"0.6\"><path stroke-dasharray=\"8 9\" fill=\"none\" stroke-width=\"1.5\" stroke=\"#868e96\" d=\"M32 0 C206.64 0, 381.29 0, 624 0 M624 0 C645.33 0, 656 10.67, 656 32 M656 32 C656 69.05, 656 106.11, 656 132 M656 132 C656 153.33, 645.33 164, 624 164 M624 164 C398.48 164, 172.96 164, 32 164 M32 164 C10.67 164, 0 153.33, 0 132 M0 132 C0 104.76, 0 77.51, 0 32 M0 32 C0 10.67, 10.67 0, 32 0\" /></g><g transform=\"translate(88 158) rotate(0 54.2 10)\" fill-opacity=\"0.6\" stroke-opacity=\"0.6\"><text dominant-baseline=\"text-before-edge\" direction=\"ltr\" style=\"white-space: pre;\" text-anchor=\"start\" fill=\"#868e96\" font-size=\"14px\" font-family=\"Virgil, Segoe UI Emoji\" y=\"0\" x=\"0\">zerobuf API</text></g><g transform=\"translate(216 360) rotate(0 150 151)\" stroke-linecap=\"round\" fill-opacity=\"0.6\" stroke-opacity=\"0.6\"><path stroke-dasharray=\"8 9\" fill=\"none\" stroke-width=\"1.5\" stroke=\"#868e96\" d=\"M32 0 C79.47 0, 126.93 0, 268 0 M268 0 C289.33 0, 300 10.67, 300 32 M300 32 C300 125.15, 300 218.3, 300 270 M300 270 C300 291.33, 289.33 302, 268 302 M268 302 C179.72 302, 91.44 302, 32 302 M32 302 C10.67 302, 0 291.33, 0 270 M0 270 C0 190.5, 0 111.01, 0 32 M0 32 C0 10.67, 10.67 0, 32 0\" /></g><g transform=\"translate(226 365) rotate(0 33.19999999999999 10)\" fill-opacity=\"0.6\" stroke-opacity=\"0.6\"><text dominant-baseline=\"text-before-edge\" direction=\"ltr\" style=\"white-space: pre;\" text-anchor=\"start\" fill=\"#868e96\" font-size=\"14px\" font-family=\"Virgil, Segoe UI Emoji\" y=\"0\" x=\"0\">Memory</text></g><g transform=\"translate(10 722) rotate(0 466 82)\" stroke-linecap=\"round\" fill-opacity=\"0.6\" stroke-opacity=\"0.6\"><path stroke-dasharray=\"8 9\" fill=\"none\" stroke-width=\"1.5\" stroke=\"#868e96\" d=\"M32 0 C218.95 0, 405.9 0, 900 0 M900 0 C921.33 0, 932 10.67, 932 32 M932 32 C932 60.2, 932 88.39, 932 132 M932 132 C932 153.33, 921.33 164, 900 164 M900 164 C563.28 164, 226.55 164, 32 164 M32 164 C10.67 164, 0 153.33, 0 132 M0 132 C0 97.11, 0 62.21, 0 32 M0 32 C0 10.67, 10.67 0, 32 0\" /></g><g transform=\"translate(20 727) rotate(0 45.800000000000004 10)\" fill-opacity=\"0.6\" stroke-opacity=\"0.6\"><text dominant-baseline=\"text-before-edge\" direction=\"ltr\" style=\"white-space: pre;\" text-anchor=\"start\" fill=\"#868e96\" font-size=\"14px\" font-family=\"Virgil, Segoe UI Emoji\" y=\"0\" x=\"0\">Consumers</text></g><g transform=\"translate(10 912) rotate(0 461 70)\" stroke-linecap=\"round\" fill-opacity=\"0.6\" stroke-opacity=\"0.6\"><path stroke-dasharray=\"8 9\" fill=\"none\" stroke-width=\"1.5\" stroke=\"#868e96\" d=\"M32 0 C226.98 0, 421.96 0, 890 0 M890 0 C911.33 0, 922 10.67, 922 32 M922 32 C922 56.26, 922 80.52, 922 108 M922 108 C922 129.33, 911.33 140, 890 140 M890 140 C681.24 140, 472.48 140, 32 140 M32 140 C10.67 140, 0 129.33, 0 108 M0 108 C0 83.79, 0 59.57, 0 32 M0 32 C0 10.67, 10.67 0, 32 0\" /></g><g transform=\"translate(20 917) rotate(0 50 10)\" fill-opacity=\"0.6\" stroke-opacity=\"0.6\"><text dominant-baseline=\"text-before-edge\" direction=\"ltr\" style=\"white-space: pre;\" text-anchor=\"start\" fill=\"#868e96\" font-size=\"14px\" font-family=\"Virgil, Segoe UI Emoji\" y=\"0\" x=\"0\">Downstream</text></g></svg>\n\\ No newline at end of file\n+  <rect fill=\"#ffffff\" height=\"896\" width=\"952\" y=\"0\" x=\"0\" /><g transform=\"translate(266 10) rotate(0 100 40)\" stroke-linecap=\"round\" fill-opacity=\"0.9\" stroke-opacity=\"0.9\"><path fill=\"#a5d8ff\" stroke-width=\"0\" stroke=\"none\" d=\"M20 0 C64.87 0, 109.74 0, 180 0 C193.33 0, 200 6.67, 200 20 C200 31.82, 200 43.65, 200 60 C200 73.33, 193.33 80, 180 80 C126.66 80, 73.32 80, 20 80 C6.67 80, 0 73.33, 0 60 C0 50.51, 0 41.02, 0 20 C0 6.67, 6.67 0, 20 0\" /><path fill=\"none\" stroke-width=\"1\" stroke=\"#1971c2\" d=\"M20 0 C53.43 0, 86.87 0, 180 0 M20 0 C63.26 0, 106.52 0, 180 0 M180 0 C193.33 0, 200 6.67, 200 20 M180 0 C193.33 0, 200 6.67, 200 20 M200 20 C200 30.92, 200 41.84, 200 60 M200 20 C200 35.99, 200 51.98, 200 60 M200 60 C200 73.33, 193.33 80, 180 80 M200 60 C200 73.33, 193.33 80, 180 80 M180 80 C141.9 80, 103.8 80, 20 80 M180 80 C122.92 80, 65.85 80, 20 80 M20 80 C6.67 80, 0 73.33, 0 60 M20 80 C6.67 80, 0 73.33, 0 60 M0 60 C0 46.71, 0 33.42, 0 20 M0 60 C0 46.14, 0 32.29, 0 20 M0 20 C0 6.67, 6.67 0, 20 0 M0 20 C0 6.67, 6.67 0, 20 0\" /></g><g transform=\"translate(276 40) rotate(0 90 10)\" fill-opacity=\"0.9\" stroke-opacity=\"0.9\"><text dominant-baseline=\"text-before-edge\" direction=\"ltr\" style=\"white-space: pre;\" text-anchor=\"middle\" fill=\"#1971c2\" font-size=\"16px\" font-family=\"Helvetica, Segoe UI Emoji\" y=\"0\" x=\"90\">Your JS/TS Code</text></g><g transform=\"translate(98 193) rotate(0 100 52)\" stroke-linecap=\"round\" fill-opacity=\"0.9\" stroke-opacity=\"0.9\"><path fill=\"#d0bfff\" stroke-width=\"0\" stroke=\"none\" d=\"M26 0 C60.91 0, 95.82 0, 174 0 C191.33 0, 200 8.67, 200 26 C200 40.4, 200 54.81, 200 78 C200 95.33, 191.33 104, 174 104 C133.3 104, 92.59 104, 26 104 C8.67 104, 0 95.33, 0 78 C0 60.07, 0 42.13, 0 26 C0 8.67, 8.67 0, 26 0\" /><path fill=\"none\" stroke-width=\"1\" stroke=\"#7048e8\" d=\"M26 0 C55.82 0, 85.63 0, 174 0 M26 0 C60.29 0, 94.57 0, 174 0 M174 0 C191.33 0, 200 8.67, 200 26 M174 0 C191.33 0, 200 8.67, 200 26 M200 26 C200 43.11, 200 60.23, 200 78 M200 26 C200 36.43, 200 46.86, 200 78 M200 78 C200 95.33, 191.33 104, 174 104 M200 78 C200 95.33, 191.33 104, 174 104 M174 104 C119.82 104, 65.65 104, 26 104 M174 104 C130.91 104, 87.82 104, 26 104 M26 104 C8.67 104, 0 95.33, 0 78 M26 104 C8.67 104, 0 95.33, 0 78 M0 78 C0 60.6, 0 43.2, 0 26 M0 78 C0 60.16, 0 42.31, 0 26 M0 26 C0 8.67, 8.67 0, 26 0 M0 26 C0 8.67, 8.67 0, 26 0\" /></g><g transform=\"translate(108 226.6) rotate(0 90 18.39999999999999)\" fill-opacity=\"0.9\" stroke-opacity=\"0.9\"><text dominant-baseline=\"text-before-edge\" direction=\"ltr\" style=\"white-space: pre;\" text-anchor=\"middle\" fill=\"#7048e8\" font-size=\"16px\" font-family=\"Helvetica, Segoe UI Emoji\" y=\"0\" x=\"90\">zerobuf.create()</text><text dominant-baseline=\"text-before-edge\" direction=\"ltr\" style=\"white-space: pre;\" text-anchor=\"middle\" fill=\"#7048e8\" font-size=\"16px\" font-family=\"Helvetica, Segoe UI Emoji\" y=\"18.4\" x=\"90\">zerobuf.read()</text></g><g transform=\"translate(514 193) rotate(0 100 52)\" stroke-linecap=\"round\" fill-opacity=\"0.9\" stroke-opacity=\"0.9\"><path fill=\"#d0bfff\" stroke-width=\"0\" stroke=\"none\" d=\"M26 0 C64.16 0, 102.33 0, 174 0 C191.33 0, 200 8.67, 200 26 C200 42.44, 200 58.88, 200 78 C200 95.33, 191.33 104, 174 104 C115.3 104, 56.61 104, 26 104 C8.67 104, 0 95.33, 0 78 C0 58.14, 0 38.27, 0 26 C0 8.67, 8.67 0, 26 0\" /><path fill=\"none\" stroke-width=\"1\" stroke=\"#7048e8\" d=\"M26 0 C74.11 0, 122.23 0, 174 0 M26 0 C80.6 0, 135.2 0, 174 0 M174 0 C191.33 0, 200 8.67, 200 26 M174 0 C191.33 0, 200 8.67, 200 26 M200 26 C200 44.08, 200 62.15, 200 78 M200 26 C200 44.7, 200 63.4, 200 78 M200 78 C200 95.33, 191.33 104, 174 104 M200 78 C200 95.33, 191.33 104, 174 104 M174 104 C116.82 104, 59.65 104, 26 104 M174 104 C127.04 104, 80.08 104, 26 104 M26 104 C8.67 104, 0 95.33, 0 78 M26 104 C8.67 104, 0 95.33, 0 78 M0 78 C0 66.27, 0 54.54, 0 26 M0 78 C0 64.13, 0 50.26, 0 26 M0 26 C0 8.67, 8.67 0, 26 0 M0 26 C0 8.67, 8.67 0, 26 0\" /></g><g transform=\"translate(524 226.6) rotate(0 90 18.39999999999999)\" fill-opacity=\"0.9\" stroke-opacity=\"0.9\"><text dominant-baseline=\"text-before-edge\" direction=\"ltr\" style=\"white-space: pre;\" text-anchor=\"middle\" fill=\"#7048e8\" font-size=\"16px\" font-family=\"Helvetica, Segoe UI Emoji\" y=\"0\" x=\"90\">defineSchema()</text><text dominant-baseline=\"text-before-edge\" direction=\"ltr\" style=\"white-space: pre;\" text-anchor=\"middle\" fill=\"#7048e8\" font-size=\"16px\" font-family=\"Helvetica, Segoe UI Emoji\" y=\"18.4\" x=\"90\">schema.create()</text></g><g transform=\"translate(236 400) rotate(0 130 40)\" stroke-linecap=\"round\" fill-opacity=\"0.9\" stroke-opacity=\"0.9\"><path fill=\"#ffa8a8\" stroke-width=\"0\" stroke=\"none\" d=\"M20 0 C75.79 0, 131.57 0, 240 0 C253.33 0, 260 6.67, 260 20 C260 33.56, 260 47.11, 260 60 C260 73.33, 253.33 80, 240 80 C188.47 80, 136.94 80, 20 80 C6.67 80, 0 73.33, 0 60 C0 49.59, 0 39.18, 0 20 C0 6.67, 6.67 0, 20 0\" /><path fill=\"none\" stroke-width=\"1\" stroke=\"#c92a2a\" d=\"M20 0 C88.95 0, 157.91 0, 240 0 M20 0 C66.57 0, 113.14 0, 240 0 M240 0 C253.33 0, 260 6.67, 260 20 M240 0 C253.33 0, 260 6.67, 260 20 M260 20 C260 32.59, 260 45.18, 260 60 M260 20 C260 35.1, 260 50.21, 260 60 M260 60 C260 73.33, 253.33 80, 240 80 M260 60 C260 73.33, 253.33 80, 240 80 M240 80 C173.79 80, 107.58 80, 20 80 M240 80 C171.48 80, 102.95 80, 20 80 M20 80 C6.67 80, 0 73.33, 0 60 M20 80 C6.67 80, 0 73.33, 0 60 M0 60 C0 49.27, 0 38.54, 0 20 M0 60 C0 45.88, 0 31.76, 0 20 M0 20 C0 6.67, 6.67 0, 20 0 M0 20 C0 6.67, 6.67 0, 20 0\" /></g><g transform=\"translate(246 412.4) rotate(0 120 27.599999999999994)\" fill-opacity=\"0.9\" stroke-opacity=\"0.9\"><text dominant-baseline=\"text-before-edge\" direction=\"ltr\" style=\"white-space: pre;\" text-anchor=\"middle\" fill=\"#c92a2a\" font-size=\"16px\" font-family=\"Helvetica, Segoe UI Emoji\" y=\"0\" x=\"120\">Arena</text><text dominant-baseline=\"text-before-edge\" direction=\"ltr\" style=\"white-space: pre;\" text-anchor=\"middle\" fill=\"#c92a2a\" font-size=\"16px\" font-family=\"Helvetica, Segoe UI Emoji\" y=\"18.4\" x=\"120\">save() / restore()</text><text dominant-baseline=\"text-before-edge\" direction=\"ltr\" style=\"white-space: pre;\" text-anchor=\"middle\" fill=\"#c92a2a\" font-size=\"16px\" font-family=\"Helvetica, Segoe UI Emoji\" y=\"36.8\" x=\"120\">alloc() / grow()</text></g><g transform=\"translate(236 582) rotate(0 130 30)\" stroke-linecap=\"round\" fill-opacity=\"0.9\" stroke-opacity=\"0.9\"><path fill=\"#ffec99\" stroke-width=\"0\" stroke=\"none\" d=\"M15 0 C70.13 0, 125.25 0, 245 0 C255 0, 260 5, 260 15 C260 22.82, 260 30.64, 260 45 C260 55, 255 60, 245 60 C189.87 60, 134.74 60, 15 60 C5 60, 0 55, 0 45 C0 38.83, 0 32.66, 0 15 C0 5, 5 0, 15 0\" /><path fill=\"none\" stroke-width=\"1\" stroke=\"#f08c00\" d=\"M15 0 C67.19 0, 119.37 0, 245 0 M15 0 C86.86 0, 158.72 0, 245 0 M245 0 C255 0, 260 5, 260 15 M245 0 C255 0, 260 5, 260 15 M260 15 C260 21.7, 260 28.41, 260 45 M260 15 C260 21.79, 260 28.58, 260 45 M260 45 C260 55, 255 60, 245 60 M260 45 C260 55, 255 60, 245 60 M245 60 C196.72 60, 148.45 60, 15 60 M245 60 C164.71 60, 84.41 60, 15 60 M15 60 C5 60, 0 55, 0 45 M15 60 C5 60, 0 55, 0 45 M0 45 C0 37.98, 0 30.97, 0 15 M0 45 C0 37.78, 0 30.56, 0 15 M0 15 C0 5, 5 0, 15 0 M0 15 C0 5, 5 0, 15 0\" /></g><g transform=\"translate(246 593.6) rotate(0 120 18.399999999999977)\" fill-opacity=\"0.9\" stroke-opacity=\"0.9\"><text dominant-baseline=\"text-before-edge\" direction=\"ltr\" style=\"white-space: pre;\" text-anchor=\"middle\" fill=\"#f08c00\" font-size=\"16px\" font-family=\"Helvetica, Segoe UI Emoji\" y=\"0\" x=\"120\">ArrayBuffer</text><text dominant-baseline=\"text-before-edge\" direction=\"ltr\" style=\"white-space: pre;\" text-anchor=\"middle\" fill=\"#f08c00\" font-size=\"16px\" font-family=\"Helvetica, Segoe UI Emoji\" y=\"18.4\" x=\"120\">(or SharedArrayBuffer)</text></g><g transform=\"translate(30 762) rotate(0 70 52)\" stroke-linecap=\"round\" fill-opacity=\"0.9\" stroke-opacity=\"0.9\"><path fill=\"#a5d8ff\" stroke-width=\"0\" stroke=\"none\" d=\"M26 0 C54.76 0, 83.52 0, 114 0 C131.33 0, 140 8.67, 140 26 C140 41.57, 140 57.15, 140 78 C140 95.33, 131.33 104, 114 104 C84.57 104, 55.14 104, 26 104 C8.67 104, 0 95.33, 0 78 C0 65.52, 0 53.04, 0 26 C0 8.67, 8.67 0, 26 0\" /><path fill=\"none\" stroke-width=\"1\" stroke=\"#1971c2\" d=\"M26 0 C45.15 0, 64.3 0, 114 0 M26 0 C50.9 0, 75.8 0, 114 0 M114 0 C131.33 0, 140 8.67, 140 26 M114 0 C131.33 0, 140 8.67, 140 26 M140 26 C140 41.74, 140 57.48, 140 78 M140 26 C140 38.27, 140 50.55, 140 78 M140 78 C140 95.33, 131.33 104, 114 104 M140 78 C140 95.33, 131.33 104, 114 104 M114 104 C84.14 104, 54.28 104, 26 104 M114 104 C86.98 104, 59.96 104, 26 104 M26 104 C8.67 104, 0 95.33, 0 78 M26 104 C8.67 104, 0 95.33, 0 78 M0 78 C0 62.59, 0 47.19, 0 26 M0 78 C0 63.38, 0 48.75, 0 26 M0 26 C0 8.67, 8.67 0, 26 0 M0 26 C0 8.67, 8.67 0, 26 0\" /></g><g transform=\"translate(40 795.6) rotate(0 60 18.399999999999977)\" fill-opacity=\"0.9\" stroke-opacity=\"0.9\"><text dominant-baseline=\"text-before-edge\" direction=\"ltr\" style=\"white-space: pre;\" text-anchor=\"middle\" fill=\"#1971c2\" font-size=\"16px\" font-family=\"Helvetica, Segoe UI Emoji\" y=\"0\" x=\"60\">\ud83d\udda5\ufe0f</text><text dominant-baseline=\"text-before-edge\" direction=\"ltr\" style=\"white-space: pre;\" text-anchor=\"middle\" fill=\"#1971c2\" font-size=\"16px\" font-family=\"Helvetica, Segoe UI Emoji\" y=\"18.4\" x=\"60\">Worker</text></g><g transform=\"translate(387 762) rotate(0 80 52)\" stroke-linecap=\"round\" fill-opacity=\"0.9\" stroke-opacity=\"0.9\"><path fill=\"#e599f7\" stroke-width=\"0\" stroke=\"none\" d=\"M26 0 C53.89 0, 81.78 0, 134 0 C151.33 0, 160 8.67, 160 26 C160 39.58, 160 53.17, 160 78 C160 95.33, 151.33 104, 134 104 C106.28 104, 78.56 104, 26 104 C8.67 104, 0 95.33, 0 78 C0 59.27, 0 40.55, 0 26 C0 8.67, 8.67 0, 26 0\" /><path fill=\"none\" stroke-width=\"1\" stroke=\"#9c36b5\" d=\"M26 0 C52.88 0, 79.77 0, 134 0 M26 0 C58.84 0, 91.69 0, 134 0 M134 0 C151.33 0, 160 8.67, 160 26 M134 0 C151.33 0, 160 8.67, 160 26 M160 26 C160 45.66, 160 65.32, 160 78 M160 26 C160 41.25, 160 56.49, 160 78 M160 78 C160 95.33, 151.33 104, 134 104 M160 78 C160 95.33, 151.33 104, 134 104 M134 104 C99.46 104, 64.92 104, 26 104 M134 104 C103.46 104, 72.92 104, 26 104 M26 104 C8.67 104, 0 95.33, 0 78 M26 104 C8.67 104, 0 95.33, 0 78 M0 78 C0 58.97, 0 39.94, 0 26 M0 78 C0 64.94, 0 51.88, 0 26 M0 26 C0 8.67, 8.67 0, 26 0 M0 26 C0 8.67, 8.67 0, 26 0\" /></g><g transform=\"translate(397 795.6) rotate(0 70 18.399999999999977)\" fill-opacity=\"0.9\" stroke-opacity=\"0.9\"><text dominant-baseline=\"text-before-edge\" direction=\"ltr\" style=\"white-space: pre;\" text-anchor=\"middle\" fill=\"#9c36b5\" font-size=\"16px\" font-family=\"Helvetica, Segoe UI Emoji\" y=\"0\" x=\"70\">WASM</text><text dominant-baseline=\"text-before-edge\" direction=\"ltr\" style=\"white-space: pre;\" text-anchor=\"middle\" fill=\"#9c36b5\" font-size=\"16px\" font-family=\"Helvetica, Segoe UI Emoji\" y=\"18.4\" x=\"70\">(Zig / Rust / C)</text></g><g transform=\"translate(762 762) rotate(0 80 52)\" stroke-linecap=\"round\" fill-opacity=\"0.9\" stroke-opacity=\"0.9\"><path fill=\"#d0bfff\" stroke-width=\"0\" stroke=\"none\" d=\"M26 0 C59.06 0, 92.13 0, 134 0 C151.33 0, 160 8.67, 160 26 C160 38.68, 160 51.36, 160 78 C160 95.33, 151.33 104, 134 104 C99.58 104, 65.15 104, 26 104 C8.67 104, 0 95.33, 0 78 C0 65.44, 0 52.88, 0 26 C0 8.67, 8.67 0, 26 0\" /><path fill=\"none\" stroke-width=\"1\" stroke=\"#7048e8\" d=\"M26 0 C59.51 0, 93.02 0, 134 0 M26 0 C66.76 0, 107.52 0, 134 0 M134 0 C151.33 0, 160 8.67, 160 26 M134 0 C151.33 0, 160 8.67, 160 26 M160 26 C160 42.45, 160 58.9, 160 78 M160 26 C160 39.9, 160 53.8, 160 78 M160 78 C160 95.33, 151.33 104, 134 104 M160 78 C160 95.33, 151.33 104, 134 104 M134 104 C104.96 104, 75.91 104, 26 104 M134 104 C94.94 104, 55.88 104, 26 104 M26 104 C8.67 104, 0 95.33, 0 78 M26 104 C8.67 104, 0 95.33, 0 78 M0 78 C0 58.17, 0 38.33, 0 26 M0 78 C0 62.88, 0 47.76, 0 26 M0 26 C0 8.67, 8.67 0, 26 0 M0 26 C0 8.67, 8.67 0, 26 0\" /></g><g transform=\"translate(772 795.6) rotate(0 70 18.399999999999977)\" fill-opacity=\"0.9\" stroke-opacity=\"0.9\"><text dominant-baseline=\"text-before-edge\" direction=\"ltr\" style=\"white-space: pre;\" text-anchor=\"middle\" fill=\"#7048e8\" font-size=\"16px\" font-family=\"Helvetica, Segoe UI Emoji\" y=\"0\" x=\"70\">\u2601\ufe0f</text><text dominant-baseline=\"text-before-edge\" direction=\"ltr\" style=\"white-space: pre;\" text-anchor=\"middle\" fill=\"#7048e8\" font-size=\"16px\" font-family=\"Helvetica, Segoe UI Emoji\" y=\"18.4\" x=\"70\">Durable Object</text></g><g stroke-linecap=\"round\"><g transform=\"translate(334 89) rotate(0 -44 50)\"><path fill=\"none\" stroke-width=\"2\" stroke=\"#7048e8\" d=\"M0 0 C-24.71 28.08, -49.43 56.17, -88 100 M0 0 C-29.65 33.69, -59.29 67.38, -88 100\" /></g><g transform=\"translate(334 89) rotate(0 -44 50)\"><path fill=\"none\" stroke-width=\"2\" stroke=\"#7048e8\" d=\"M-77.08 72.06 C-80.15 79.91, -83.21 87.75, -88 100 M-77.08 72.06 C-80.76 81.47, -84.44 90.88, -88 100\" /></g><g transform=\"translate(334 89) rotate(0 -44 50)\"><path fill=\"none\" stroke-width=\"2\" stroke=\"#7048e8\" d=\"M-61.67 85.62 C-69.07 89.66, -76.46 93.69, -88 100 M-61.67 85.62 C-70.54 90.46, -79.41 95.31, -88 100\" /></g></g><mask /><g transform=\"translate(284.6 130) rotate(0 37.39999999999999 10)\"><text dominant-baseline=\"text-before-edge\" direction=\"ltr\" style=\"white-space: pre;\" text-anchor=\"middle\" fill=\"#1e1e1e\" font-size=\"14px\" font-family=\"Virgil, Segoe UI Emoji\" y=\"0\" x=\"37.400000000000006\">dynamic</text></g><g stroke-linecap=\"round\"><g transform=\"translate(376 87) rotate(0 87 53.5)\"><path fill=\"none\" stroke-width=\"2\" stroke=\"#7048e8\" d=\"M0 0 C61.79 38, 123.58 75.99, 174 107 M0 0 C53.49 32.89, 106.98 65.78, 174 107\" /></g><g transform=\"translate(376 87) rotate(0 87 53.5)\"><path fill=\"none\" stroke-width=\"2\" stroke=\"#7048e8\" d=\"M144.61 100.97 C155.05 103.11, 165.48 105.25, 174 107 M144.61 100.97 C153.65 102.83, 162.68 104.68, 174 107\" /></g><g transform=\"translate(376 87) rotate(0 87 53.5)\"><path fill=\"none\" stroke-width=\"2\" stroke=\"#7048e8\" d=\"M155.36 83.49 C161.98 91.84, 168.6 100.19, 174 107 M155.36 83.49 C161.09 90.72, 166.82 97.95, 174 107\" /></g></g><mask /><g transform=\"translate(482.6 130) rotate(0 58.400000000000034 10)\"><text dominant-baseline=\"text-before-edge\" direction=\"ltr\" style=\"white-space: pre;\" text-anchor=\"middle\" fill=\"#1e1e1e\" font-size=\"14px\" font-family=\"Virgil, Segoe UI Emoji\" y=\"0\" x=\"58.400000000000006\">fixed layout</text></g><g stroke-linecap=\"round\"><g transform=\"translate(239 293) rotate(0 43.5 49.5)\"><path fill=\"none\" stroke-width=\"2\" stroke=\"#c92a2a\" d=\"M0 0 C29.21 33.24, 58.43 66.49, 87 99 M0 0 C31.88 36.27, 63.75 72.54, 87 99\" /></g><g transform=\"translate(239 293) rotate(0 43.5 49.5)\"><path fill=\"none\" stroke-width=\"2\" stroke=\"#c92a2a\" d=\"M60.68 84.6 C69.52 89.43, 78.36 94.27, 87 99 M60.68 84.6 C70.33 89.87, 79.97 95.15, 87 99\" /></g><g transform=\"translate(239 293) rotate(0 43.5 49.5)\"><path fill=\"none\" stroke-width=\"2\" stroke=\"#c92a2a\" d=\"M76.1 71.05 C79.76 80.44, 83.42 89.82, 87 99 M76.1 71.05 C80.09 81.29, 84.09 91.53, 87 99\" /></g></g><mask /><g transform=\"translate(284.4 336) rotate(0 62.60000000000001 10)\"><text dominant-baseline=\"text-before-edge\" direction=\"ltr\" style=\"white-space: pre;\" text-anchor=\"middle\" fill=\"#1e1e1e\" font-size=\"14px\" font-family=\"Virgil, Segoe UI Emoji\" y=\"0\" x=\"62.6\">encode/decode</text></g><g stroke-linecap=\"round\"><g transform=\"translate(559 289) rotate(0 -68.5 53)\"><path fill=\"none\" stroke-width=\"2\" stroke=\"#c92a2a\" d=\"M0 0 C-28.13 21.76, -56.25 43.52, -137 106 M0 0 C-49.08 37.97, -98.16 75.95, -137 106\" /></g><g transform=\"translate(559 289) rotate(0 -68.5 53)\"><path fill=\"none\" stroke-width=\"2\" stroke=\"#c92a2a\" d=\"M-120.98 80.63 C-124.27 85.84, -127.56 91.05, -137 106 M-120.98 80.63 C-126.72 89.72, -132.46 98.81, -137 106\" /></g><g transform=\"translate(559 289) rotate(0 -68.5 53)\"><path fill=\"none\" stroke-width=\"2\" stroke=\"#c92a2a\" d=\"M-108.42 96.86 C-114.29 98.74, -120.16 100.62, -137 106 M-108.42 96.86 C-118.66 100.14, -128.9 103.41, -137 106\" /></g></g><mask /><g transform=\"translate(482.2 336) rotate(0 87.79999999999998 10)\"><text dominant-baseline=\"text-before-edge\" direction=\"ltr\" style=\"white-space: pre;\" text-anchor=\"middle\" fill=\"#1e1e1e\" font-size=\"14px\" font-family=\"Virgil, Segoe UI Emoji\" y=\"0\" x=\"87.8\">precomputed offsets</text></g><g stroke-linecap=\"round\"><g transform=\"translate(366 480) rotate(0 0 45.5)\"><path fill=\"none\" stroke-width=\"2\" stroke=\"#f08c00\" d=\"M0 0 C0 31.52, 0 63.05, 0 91 M0 0 C0 24.62, 0 49.23, 0 91\" /></g><g transform=\"translate(366 480) rotate(0 0 45.5)\"><path fill=\"none\" stroke-width=\"2\" stroke=\"#f08c00\" d=\"M-10.26 62.81 C-6.71 72.58, -3.15 82.34, 0 91 M-10.26 62.81 C-7.49 70.43, -4.71 78.06, 0 91\" /></g><g transform=\"translate(366 480) rotate(0 0 45.5)\"><path fill=\"none\" stroke-width=\"2\" stroke=\"#f08c00\" d=\"M10.26 62.81 C6.71 72.58, 3.15 82.34, 0 91 M10.26 62.81 C7.49 70.43, 4.71 78.06, 0 91\" /></g></g><mask /><g transform=\"translate(358.6 519) rotate(0 58.400000000000006 10)\"><text dominant-baseline=\"text-before-edge\" direction=\"ltr\" style=\"white-space: pre;\" text-anchor=\"middle\" fill=\"#1e1e1e\" font-size=\"14px\" font-family=\"Virgil, Segoe UI Emoji\" y=\"0\" x=\"58.400000000000006\">reads/writes</text></g><g stroke-linecap=\"round\"><g transform=\"translate(329 641) rotate(0 -85.5 64)\"><path fill=\"none\" stroke-width=\"2\" stroke=\"#1971c2\" d=\"M0 0 C-46.53 34.83, -93.05 69.65, -171 128 M0 0 C-61.67 46.16, -123.34 92.33, -171 128\" /></g><g transform=\"translate(329 641) rotate(0 -85.5 64)\"><path fill=\"none\" stroke-width=\"2\" stroke=\"#1971c2\" d=\"M-154.58 102.89 C-159.05 109.72, -163.52 116.56, -171 128 M-154.58 102.89 C-160.5 111.95, -166.42 121, -171 128\" /></g><g transform=\"translate(329 641) rotate(0 -85.5 64)\"><path fill=\"none\" stroke-width=\"2\" stroke=\"#1971c2\" d=\"M-142.28 119.32 C-150.1 121.68, -157.91 124.04, -171 128 M-142.28 119.32 C-152.64 122.45, -163 125.58, -171 128\" /></g></g><mask /><g transform=\"translate(198.60000000000002 658) rotate(0 54.19999999999999 10)\"><text dominant-baseline=\"text-before-edge\" direction=\"ltr\" style=\"white-space: pre;\" text-anchor=\"middle\" fill=\"#1e1e1e\" font-size=\"14px\" font-family=\"Virgil, Segoe UI Emoji\" y=\"0\" x=\"54.2\">postMessage</text><text dominant-baseline=\"text-before-edge\" direction=\"ltr\" style=\"white-space: pre;\" text-anchor=\"middle\" fill=\"#1e1e1e\" font-size=\"14px\" font-family=\"Virgil, Segoe UI Emoji\" y=\"17.5\" x=\"54.2\">(zero-copy)</text></g><g stroke-linecap=\"round\"><g transform=\"translate(334 642) rotate(0 52 56)\"><path fill=\"none\" stroke-width=\"2\" stroke=\"#9c36b5\" d=\"M0 0 C34.75 37.42, 69.5 74.85, 104 112 M0 0 C23.7 25.52, 47.39 51.04, 104 112\" /></g><g transform=\"translate(334 642) rotate(0 52 56)\"><path fill=\"none\" stroke-width=\"2\" stroke=\"#9c36b5\" d=\"M77.3 98.32 C86.22 102.89, 95.14 107.46, 104 112 M77.3 98.32 C83.38 101.44, 89.47 104.56, 104 112\" /></g><g transform=\"translate(334 642) rotate(0 52 56)\"><path fill=\"none\" stroke-width=\"2\" stroke=\"#9c36b5\" d=\"M92.34 84.36 C96.23 93.6, 100.13 102.83, 104 112 M92.34 84.36 C94.99 90.66, 97.65 96.96, 104 112\" /></g></g><mask /><g transform=\"translate(408.4 722) rotate(0 62.599999999999994 10)\"><text dominant-baseline=\"text-before-edge\" direction=\"ltr\" style=\"white-space: pre;\" text-anchor=\"middle\" fill=\"#1e1e1e\" font-size=\"14px\" font-family=\"Virgil, Segoe UI Emoji\" y=\"0\" x=\"62.6\">memory.buffer</text><text dominant-baseline=\"text-before-edge\" direction=\"ltr\" style=\"white-space: pre;\" text-anchor=\"middle\" fill=\"#1e1e1e\" font-size=\"14px\" font-family=\"Virgil, Segoe UI Emoji\" y=\"17.5\" x=\"62.6\">(shared)</text></g><g stroke-linecap=\"round\"><g transform=\"translate(479 639) rotate(0 143.5 70)\"><path fill=\"none\" stroke-width=\"2\" stroke=\"#7048e8\" d=\"M0 0 C25.28 15.71, 50.55 31.43, 74 46 M0 0 C24.72 15.37, 49.45 30.74, 74 46 M74 46 C146.48 77.99, 218.96 109.97, 287 140 M74 46 C134.34 72.63, 194.68 99.26, 287 140\" /></g><g transform=\"translate(479 639) rotate(0 143.5 70)\"><path fill=\"none\" stroke-width=\"2\" stroke=\"#7048e8\" d=\"M257.07 138.01 C267.29 138.69, 277.52 139.37, 287 140 M257.07 138.01 C267.07 138.67, 277.07 139.34, 287 140\" /></g><g transform=\"translate(479 639) rotate(0 143.5 70)\"><path fill=\"none\" stroke-width=\"2\" stroke=\"#7048e8\" d=\"M265.35 119.23 C272.75 126.33, 280.14 133.42, 287 140 M265.35 119.23 C272.58 126.17, 279.82 133.11, 287 140\" /></g></g><mask /><g transform=\"translate(614.8 672) rotate(0 54.19999999999999 10)\"><text dominant-baseline=\"text-before-edge\" direction=\"ltr\" style=\"white-space: pre;\" text-anchor=\"middle\" fill=\"#1e1e1e\" font-size=\"14px\" font-family=\"Virgil, Segoe UI Emoji\" y=\"0\" x=\"54.2\">storage.put</text><text dominant-baseline=\"text-before-edge\" direction=\"ltr\" style=\"white-space: pre;\" text-anchor=\"middle\" fill=\"#1e1e1e\" font-size=\"14px\" font-family=\"Virgil, Segoe UI Emoji\" y=\"17.5\" x=\"54.2\">(binary)</text></g><g transform=\"translate(78 153) rotate(0 328 82)\" stroke-linecap=\"round\" fill-opacity=\"0.6\" stroke-opacity=\"0.6\"><path stroke-dasharray=\"8 9\" fill=\"none\" stroke-width=\"1.5\" stroke=\"#868e96\" d=\"M32 0 C252.38 0, 472.77 0, 624 0 M624 0 C645.33 0, 656 10.67, 656 32 M656 32 C656 52.39, 656 72.77, 656 132 M656 132 C656 153.33, 645.33 164, 624 164 M624 164 C452.18 164, 280.36 164, 32 164 M32 164 C10.67 164, 0 153.33, 0 132 M0 132 C0 94.75, 0 57.51, 0 32 M0 32 C0 10.67, 10.67 0, 32 0\" /></g><g transform=\"translate(88 158) rotate(0 54.2 10)\" fill-opacity=\"0.6\" stroke-opacity=\"0.6\"><text dominant-baseline=\"text-before-edge\" direction=\"ltr\" style=\"white-space: pre;\" text-anchor=\"start\" fill=\"#868e96\" font-size=\"14px\" font-family=\"Virgil, Segoe UI Emoji\" y=\"0\" x=\"0\">zerobuf API</text></g><g transform=\"translate(216 360) rotate(0 150 151)\" stroke-linecap=\"round\" fill-opacity=\"0.6\" stroke-opacity=\"0.6\"><path stroke-dasharray=\"8 9\" fill=\"none\" stroke-width=\"1.5\" stroke=\"#868e96\" d=\"M32 0 C111.4 0, 190.81 0, 268 0 M268 0 C289.33 0, 300 10.67, 300 32 M300 32 C300 117.52, 300 203.03, 300 270 M300 270 C300 291.33, 289.33 302, 268 302 M268 302 C198.8 302, 129.6 302, 32 302 M32 302 C10.67 302, 0 291.33, 0 270 M0 270 C0 200.21, 0 130.41, 0 32 M0 32 C0 10.67, 10.67 0, 32 0\" /></g><g transform=\"translate(226 365) rotate(0 33.19999999999999 10)\" fill-opacity=\"0.6\" stroke-opacity=\"0.6\"><text dominant-baseline=\"text-before-edge\" direction=\"ltr\" style=\"white-space: pre;\" text-anchor=\"start\" fill=\"#868e96\" font-size=\"14px\" font-family=\"Virgil, Segoe UI Emoji\" y=\"0\" x=\"0\">Memory</text></g><g transform=\"translate(10 722) rotate(0 466 82)\" stroke-linecap=\"round\" fill-opacity=\"0.6\" stroke-opacity=\"0.6\"><path stroke-dasharray=\"8 9\" fill=\"none\" stroke-width=\"1.5\" stroke=\"#868e96\" d=\"M32 0 C352.71 0, 673.42 0, 900 0 M900 0 C921.33 0, 932 10.67, 932 32 M932 32 C932 52.52, 932 73.03, 932 132 M932 132 C932 153.33, 921.33 164, 900 164 M900 164 C604.74 164, 309.49 164, 32 164 M32 164 C10.67 164, 0 153.33, 0 132 M0 132 C0 110.73, 0 89.46, 0 32 M0 32 C0 10.67, 10.67 0, 32 0\" /></g><g transform=\"translate(20 727) rotate(0 45.800000000000004 10)\" fill-opacity=\"0.6\" stroke-opacity=\"0.6\"><text dominant-baseline=\"text-before-edge\" direction=\"ltr\" style=\"white-space: pre;\" text-anchor=\"start\" fill=\"#868e96\" font-size=\"14px\" font-family=\"Virgil, Segoe UI Emoji\" y=\"0\" x=\"0\">Consumers</text></g></svg>\n\\ No newline at end of file"
    }
  ]
}
