{
  "message": "fix(dep): sort human dependency lists by priority (beads_rust-kqok)",
  "files": [
    {
      "sha": "0e865d00af6a8fbd04c77bbd9d0d518e401f6572",
      "filename": ".beads/issues.jsonl",
      "status": "modified",
      "additions": 1,
      "deletions": 1,
      "changes": 2,
      "blob_url": "https://github.com/Dicklesworthstone/beads_rust/blob/4f55a3ede5de73e24eaf53f88044029c293c0102/.beads%2Fissues.jsonl",
      "raw_url": "https://github.com/Dicklesworthstone/beads_rust/raw/4f55a3ede5de73e24eaf53f88044029c293c0102/.beads%2Fissues.jsonl",
      "contents_url": "https://api.github.com/repos/Dicklesworthstone/beads_rust/contents/.beads%2Fissues.jsonl?ref=4f55a3ede5de73e24eaf53f88044029c293c0102",
      "patch": "@@ -446,7 +446,7 @@\n {\"id\":\"beads_rust-kkdq\",\"title\":\"Rustfmt cleanup for tests/benches\",\"description\":\"Manually apply rustfmt diffs to files touched in recent test/bench updates so cargo fmt --check passes without running rustfmt (per no-script rule).\",\"notes\":\"Applied rustfmt diffs manually across benches/storage_perf.rs and test files (conformance.rs, e2e_completions.rs, e2e_defer.rs, e2e_history.rs, e2e_lint.rs, e2e_upgrade.rs, proptest_hash.rs). cargo fmt --check now passes.\",\"status\":\"closed\",\"priority\":3,\"issue_type\":\"task\",\"assignee\":\"DustyHarbor\",\"owner\":\"jeff141421@gmail.com\",\"created_at\":\"2026-01-17T18:02:30.328397717Z\",\"created_by\":\"Dicklesworthstone\",\"updated_at\":\"2026-01-17T18:06:44.125703680Z\",\"closed_at\":\"2026-01-17T18:06:44.125703680Z\",\"close_reason\":\"Rustfmt diffs applied; cargo fmt --check clean\",\"source_repo\":\".\",\"compaction_level\":0,\"original_size\":0,\"dependencies\":[{\"issue_id\":\"beads_rust-kkdq\",\"depends_on_id\":\"beads_rust-ums\",\"type\":\"discovered-from\",\"created_at\":\"2026-03-08T22:47:30Z\",\"created_by\":\"import\",\"metadata\":\"{}\",\"thread_id\":\"\"}]}\n {\"id\":\"beads_rust-kmls\",\"title\":\"Fix create_issue to persist full issue fields\",\"description\":\"create_issue previously inserted only a subset of columns, causing tombstone deleted_at to be dropped and export retention tests to fail. Update insert to include all issue fields.\",\"notes\":\"Expanded create_issue INSERT to include all issue columns; reran targeted tombstone export test.\",\"status\":\"closed\",\"priority\":2,\"issue_type\":\"task\",\"estimated_minutes\":0,\"created_at\":\"2026-01-16T19:04:38.912040091Z\",\"created_by\":\"Dicklesworthstone\",\"updated_at\":\"2026-01-16T19:04:48.995085829Z\",\"closed_at\":\"2026-01-16T19:04:48.995085829Z\",\"close_reason\":\"Completed\",\"source_repo\":\".\",\"compaction_level\":0,\"compacted_at_commit\":\"\",\"original_size\":0}\n {\"id\":\"beads_rust-kptp\",\"title\":\"Integrate rich output into lint command\",\"description\":\"## Command: br lint [--fix]\\n\\n### Traffic Level: LOW-MEDIUM\\nData quality checks with optional auto-fix.\\n\\n### Current Implementation\\nLocation: src/cli/commands/lint.rs\\nOutput: List of warnings/errors\\n\\n### Integration Steps\\n1. Show progress for large issue sets\\n2. Group warnings by type\\n3. Highlight fixable vs manual issues\\n4. Show fix preview with --dry-run\\n\\n### Visual Enhancement\\n```\\n\u256d\u2500 Lint Results \u2500\u2500\u2500\u2500\u2500\u2500\u2500\u2500\u2500\u2500\u2500\u2500\u2500\u2500\u2500\u2500\u2500\u2500\u2500\u2500\u2500\u2500\u2500\u2500\u2500\u2500\u2500\u2500\u2500\u2500\u2500\u2500\u2500\u2500\u2500\u2500\u2500\u2500\u256e\\n\u2502                                                     \u2502\\n\u2502  \u2713 156 issues checked                               \u2502\\n\u2502                                                     \u2502\\n\u2502  \u26a0 3 warnings:                                      \u2502\\n\u2502  \u251c\u2500\u2500 beads_rust-abc1  Missing description           \u2502\\n\u2502  \u251c\u2500\u2500 beads_rust-def2  Orphaned dependency           \u2502\\n\u2502  \u2514\u2500\u2500 beads_rust-ghi3  Invalid priority (fixed)      \u2502\\n\u2502                                                     \u2502\\n\u2502  \u274c 1 error:                                         \u2502\\n\u2502  \u2514\u2500\u2500 beads_rust-jkl4  Circular dependency detected  \u2502\\n\u2502                                                     \u2502\\n\u2502  Auto-fixable: 1 issue                              \u2502\\n\u2502  Run with --fix to apply fixes                      \u2502\\n\u2502                                                     \u2502\\n\u2570\u2500\u2500\u2500\u2500\u2500\u2500\u2500\u2500\u2500\u2500\u2500\u2500\u2500\u2500\u2500\u2500\u2500\u2500\u2500\u2500\u2500\u2500\u2500\u2500\u2500\u2500\u2500\u2500\u2500\u2500\u2500\u2500\u2500\u2500\u2500\u2500\u2500\u2500\u2500\u2500\u2500\u2500\u2500\u2500\u2500\u2500\u2500\u2500\u2500\u2500\u2500\u2500\u2500\u256f\\n```\\n\\n---\\n\\n## Testing Requirements\\n\\n### Unit Tests\\nLocation: tests/cli/lint_tests.rs\\n\\n```rust\\n#[test]\\nfn test_lint_groups_by_type() {\\n    let warnings = create_lint_warnings();\\n    let ctx = OutputContext::plain();\\n    let output = render_lint_results(&warnings, &ctx);\\n    assert!(output.contains(\\\"warning\\\") || output.contains(\\\"\u26a0\\\"));\\n}\\n\\n#[test]\\nfn test_lint_json_unchanged() {\\n    let current = run_lint_json();\\n    let baseline = load_fixture(\\\"tests/fixtures/json_baseline/lint.json\\\");\\n    assert_json_eq!(current, baseline);\\n}\\n\\n#[test]\\nfn test_lint_shows_fixable() {\\n    let warnings = vec![LintWarning { fixable: true, .. }];\\n    let ctx = OutputContext::plain();\\n    let output = render_lint_results(&warnings, &ctx);\\n    assert!(output.contains(\\\"fixable\\\") || output.contains(\\\"--fix\\\"));\\n}\\n```\\n\\n### E2E Test Script\\nLocation: tests/e2e/lint_e2e.sh\\n\\n```bash\\n#!/bin/bash\\nset -euo pipefail\\nsource \\\"$(dirname \\\"$0\\\")/../common/test_helpers.sh\\\"\\n\\nlog_info \\\"=== E2E: Lint Command ===\\\"\\nsetup_test_db\\ncreate_issues_with_lint_problems\\n\\nlog_step \\\"Testing basic lint\\\"\\nOUTPUT=$(br lint 2>&1)\\nassert_contains \\\"$OUTPUT\\\" \\\"checked\\\" \\\"Should show checked count\\\"\\nlog_pass \\\"Basic lint works\\\"\\n\\nlog_step \\\"Testing --fix dry run\\\"\\nFIX_OUTPUT=$(br lint --fix --dry-run 2>&1)\\nlog_pass \\\"--fix dry run works\\\"\\n\\nlog_step \\\"Testing JSON output\\\"\\nJSON_OUTPUT=$(br lint --json)\\necho \\\"$JSON_OUTPUT\\\" | jq . > /dev/null\\nlog_pass \\\"JSON output valid\\\"\\n\\nlog_success \\\"=== Lint command E2E: ALL PASSED ===\\\"\\n```\\n\\n### Logging Requirements\\n- Log issue count being checked\\n- Log warning/error counts by type\\n- Log fixes applied (with --fix)\",\"status\":\"closed\",\"priority\":2,\"issue_type\":\"task\",\"created_at\":\"2026-01-19T20:35:39.832516428Z\",\"created_by\":\"ubuntu\",\"updated_at\":\"2026-01-20T18:37:41.737560347Z\",\"closed_at\":\"2026-01-20T18:37:41.737509110Z\",\"close_reason\":\"Completed\",\"source_repo\":\".\",\"compaction_level\":0,\"original_size\":0,\"dependencies\":[{\"issue_id\":\"beads_rust-kptp\",\"depends_on_id\":\"beads_rust-1rpr\",\"type\":\"blocks\",\"created_at\":\"2026-03-08T22:47:30Z\",\"created_by\":\"import\",\"metadata\":\"{}\",\"thread_id\":\"\"},{\"issue_id\":\"beads_rust-kptp\",\"depends_on_id\":\"beads_rust-31nl\",\"type\":\"parent-child\",\"created_at\":\"2026-03-08T22:47:30Z\",\"created_by\":\"import\",\"metadata\":\"{}\",\"thread_id\":\"\"}]}\n-{\"id\":\"beads_rust-kqok\",\"title\":\"Track: dep list should support sorting by priority instead of only by ID\",\"description\":\"SUBTASK 7.3 (DEFERRED FEATURE): src/cli/commands/dep.rs:903 contains:\\n  \\\"For now, let us sort by ID to be deterministic, or fetch details. Priority sorting would require fetching issues.\\\"\\n\\nCURRENT BEHAVIOR: The dep list command sorts dependencies by ID string (lexicographic). This is deterministic but not useful for triage \u2014 a user running br dep list bd-X wants to see the highest-priority blockers first.\\n\\nDESIRED BEHAVIOR: Add a --sort=priority flag (or make priority the default) that fetches the full issue for each dependency and sorts by priority descending.\\n\\nIMPLEMENTATION CONSIDERATIONS:\\n- The current code avoids fetching issues for performance (dep list only queries the dependencies table)\\n- Priority sorting requires N additional get_issue() calls (one per dependency) which adds latency for issues with many deps\\n- Could batch-fetch with a single SQL query: SELECT * FROM issues WHERE id IN (dep1, dep2, ...) ORDER BY priority ASC\\n- For most issues, N < 10 deps, so the performance impact is negligible\\n- Could cache the results since the same issue might appear in multiple dep lists\\n- Consider making ID sort the default for --json (deterministic, machine-friendly) and priority sort the default for interactive/rich mode (human-friendly)\\n\\nPRIORITY: P4/backlog because the current behavior is correct (deterministic, complete), just not optimally sorted for human use.\",\"status\":\"open\",\"priority\":4,\"issue_type\":\"feature\",\"created_at\":\"2026-03-25T03:09:41.314015226Z\",\"created_by\":\"ubuntu\",\"updated_at\":\"2026-03-25T03:33:41.871596047Z\",\"source_repo\":\".\",\"compaction_level\":0,\"original_size\":0}\n+{\"id\":\"beads_rust-kqok\",\"title\":\"Track: dep list should support sorting by priority instead of only by ID\",\"description\":\"SUBTASK 7.3 (DEFERRED FEATURE): src/cli/commands/dep.rs:903 contains:\\n  \\\"For now, let us sort by ID to be deterministic, or fetch details. Priority sorting would require fetching issues.\\\"\\n\\nCURRENT BEHAVIOR: The dep list command sorts dependencies by ID string (lexicographic). This is deterministic but not useful for triage \u2014 a user running br dep list bd-X wants to see the highest-priority blockers first.\\n\\nDESIRED BEHAVIOR: Add a --sort=priority flag (or make priority the default) that fetches the full issue for each dependency and sorts by priority descending.\\n\\nIMPLEMENTATION CONSIDERATIONS:\\n- The current code avoids fetching issues for performance (dep list only queries the dependencies table)\\n- Priority sorting requires N additional get_issue() calls (one per dependency) which adds latency for issues with many deps\\n- Could batch-fetch with a single SQL query: SELECT * FROM issues WHERE id IN (dep1, dep2, ...) ORDER BY priority ASC\\n- For most issues, N < 10 deps, so the performance impact is negligible\\n- Could cache the results since the same issue might appear in multiple dep lists\\n- Consider making ID sort the default for --json (deterministic, machine-friendly) and priority sort the default for interactive/rich mode (human-friendly)\\n\\nPRIORITY: P4/backlog because the current behavior is correct (deterministic, complete), just not optimally sorted for human use.\",\"status\":\"closed\",\"priority\":4,\"issue_type\":\"feature\",\"created_at\":\"2026-03-25T03:09:41.314015226Z\",\"created_by\":\"ubuntu\",\"updated_at\":\"2026-04-21T15:58:59.092024775Z\",\"closed_at\":\"2026-04-21T15:58:59.091676463Z\",\"close_reason\":\"Made human dep list output priority-aware while preserving JSON/TOON machine output order\",\"source_repo\":\".\",\"compaction_level\":0,\"original_size\":0}\n {\"id\":\"beads_rust-kr5i\",\"title\":\"E2E tests: label command\",\"description\":\"# E2E Tests for `label` Command\\n\\n## Commands to Test\\n- `br label add <issue_id> <label>` - Add label to issue\\n- `br label remove <issue_id> <label>` - Remove label from issue\\n- `br label list` - List all labels in workspace\\n- `br label --json` - JSON output mode\\n\\n## Test Cases\\n### Success Paths\\n1. Add single label, verify via show\\n2. Add multiple labels to same issue\\n3. Remove label, verify removed\\n4. List all labels across issues\\n5. Add same label to multiple issues\\n\\n### Error Cases\\n6. Add label to non-existent issue \u2192 error\\n7. Remove non-existent label \u2192 error or no-op\\n8. Invalid label format (if any validation)\\n\\n### Edge Cases\\n9. Label with special characters\\n10. Very long label name\\n11. Case sensitivity (bug vs BUG)\\n12. Label on closed issue\\n\\n## Acceptance Criteria\\n- [ ] Test file: tests/e2e_labels.rs\\n- [ ] 12+ test functions\\n- [ ] Verify label persistence in JSONL export\",\"status\":\"closed\",\"priority\":2,\"issue_type\":\"task\",\"assignee\":\"GreenSparrow\",\"owner\":\"jeff141421@gmail.com\",\"created_at\":\"2026-01-17T14:25:51.989260181Z\",\"created_by\":\"Dicklesworthstone\",\"updated_at\":\"2026-01-17T14:44:10.369726951Z\",\"closed_at\":\"2026-01-17T14:44:10.369726951Z\",\"close_reason\":\"Implemented 16 E2E tests for label command in tests/e2e_labels.rs - all tests passed\",\"source_repo\":\".\",\"compaction_level\":0,\"original_size\":0,\"dependencies\":[{\"issue_id\":\"beads_rust-kr5i\",\"depends_on_id\":\"beads_rust-oxmd\",\"type\":\"parent-child\",\"created_at\":\"2026-03-08T22:47:30Z\",\"created_by\":\"import\",\"metadata\":\"{}\",\"thread_id\":\"\"}]}\n {\"id\":\"beads_rust-ku1s\",\"title\":\"E2E scenarios: sync safety suite (git/path/atomic/preflight)\",\"description\":\"Implement the documented sync E2E suite with full artifacts and safety assertions.\\n\\nCoverage\\n- git safety (no commits, no .git mutation)\\n- path allowlist + traversal rejection\\n- atomic export (temp + rename) and failure injection\\n- preflight validation (conflict markers, invalid JSONL)\\n\\nAcceptance\\n- Matches docs/E2E_SYNC_TESTS.md structure.\\n- Produces snapshot diffs and structured failure artifacts.\",\"status\":\"closed\",\"priority\":1,\"issue_type\":\"task\",\"owner\":\"jeff141421@gmail.com\",\"created_at\":\"2026-01-18T03:41:33.414146281Z\",\"created_by\":\"Dicklesworthstone\",\"updated_at\":\"2026-01-18T04:45:08.320604696Z\",\"closed_at\":\"2026-01-18T04:45:08.320604696Z\",\"close_reason\":\"All sync safety E2E tests implemented and passing: git_safety (73 tests), artifacts (75), preflight_integration (75), fuzz_edge_cases (78), failure_injection (77). Matches docs/E2E_SYNC_TESTS.md structure.\",\"source_repo\":\".\",\"compaction_level\":0,\"original_size\":0,\"dependencies\":[{\"issue_id\":\"beads_rust-ku1s\",\"depends_on_id\":\"beads_rust-5y9e\",\"type\":\"blocks\",\"created_at\":\"2026-03-08T22:47:30Z\",\"created_by\":\"import\",\"metadata\":\"{}\",\"thread_id\":\"\"},{\"issue_id\":\"beads_rust-ku1s\",\"depends_on_id\":\"beads_rust-7wqg\",\"type\":\"blocks\",\"created_at\":\"2026-03-08T22:47:30Z\",\"created_by\":\"import\",\"metadata\":\"{}\",\"thread_id\":\"\"},{\"issue_id\":\"beads_rust-ku1s\",\"depends_on_id\":\"beads_rust-ag35\",\"type\":\"parent-child\",\"created_at\":\"2026-03-08T22:47:30Z\",\"created_by\":\"import\",\"metadata\":\"{}\",\"thread_id\":\"\"},{\"issue_id\":\"beads_rust-ku1s\",\"depends_on_id\":\"beads_rust-enep\",\"type\":\"blocks\",\"created_at\":\"2026-03-08T22:47:30Z\",\"created_by\":\"import\",\"metadata\":\"{}\",\"thread_id\":\"\"},{\"issue_id\":\"beads_rust-ku1s\",\"depends_on_id\":\"beads_rust-ir0t\",\"type\":\"blocks\",\"created_at\":\"2026-03-08T22:47:30Z\",\"created_by\":\"import\",\"metadata\":\"{}\",\"thread_id\":\"\"},{\"issue_id\":\"beads_rust-ku1s\",\"depends_on_id\":\"beads_rust-o1az\",\"type\":\"blocks\",\"created_at\":\"2026-03-08T22:47:30Z\",\"created_by\":\"import\",\"metadata\":\"{}\",\"thread_id\":\"\"},{\"issue_id\":\"beads_rust-ku1s\",\"depends_on_id\":\"beads_rust-r23m\",\"type\":\"blocks\",\"created_at\":\"2026-03-08T22:47:30Z\",\"created_by\":\"import\",\"metadata\":\"{}\",\"thread_id\":\"\"},{\"issue_id\":\"beads_rust-ku1s\",\"depends_on_id\":\"beads_rust-rkuz\",\"type\":\"blocks\",\"created_at\":\"2026-03-08T22:47:30Z\",\"created_by\":\"import\",\"metadata\":\"{}\",\"thread_id\":\"\"},{\"issue_id\":\"beads_rust-ku1s\",\"depends_on_id\":\"beads_rust-x7z8\",\"type\":\"blocks\",\"created_at\":\"2026-03-08T22:47:30Z\",\"created_by\":\"import\",\"metadata\":\"{}\",\"thread_id\":\"\"}],\"comments\":[{\"id\":157,\"issue_id\":\"beads_rust-ku1s\",\"author\":\"Dicklesworthstone\",\"text\":\"Sync suite should mirror docs/E2E_SYNC_TESTS.md: git safety, path allowlist, atomic export, preflight rejection, and failure-injection with persisted artifacts. Use full tree snapshots to assert no non-.beads files changed.\",\"created_at\":\"2026-01-18T03:44:00Z\"}]}\n {\"id\":\"beads_rust-kvfz\",\"title\":\"Benchmark baselines + regression thresholds\",\"description\":\"Define baseline expectations and regression detection for benchmark runs.\\n\\n## Scope\\nEstablish performance baselines and automated regression detection for br commands.\\n\\n### Baseline Metrics\\n\\n**Per Command Group:**\\n- `list` operations: median time, p95 time, RSS peak\\n- `search` operations: median time, p95 time for various query complexities\\n- `create` operations: median time including JSONL flush\\n- `sync` operations: import/export time for various dataset sizes\\n- `ready`/`blocked` operations: time including dependency resolution\\n\\n**Per Dataset Size:**\\n- Small (100 issues): baseline for quick feedback\\n- Medium (1,000 issues): typical project size\\n- Large (10,000 issues): stress testing\\n- XL (100,000 issues): scale limits\\n\\n### Statistical Methodology\\n\\n**Sampling:**\\n- Minimum 10 runs per measurement (configurable via BR_BENCH_RUNS)\\n- Warm-up run discarded before measurement\\n- Cold-start measured separately from warm-start\\n\\n**Metrics:**\\n- Median (p50): primary metric for stability\\n- p95: tail latency for worst-case\\n- RSS peak: memory high-water mark\\n- RSS delta: memory growth during operation\\n\\n**Outlier Handling:**\\n- Use IQR method: discard values outside [Q1 - 1.5*IQR, Q3 + 1.5*IQR]\\n- Report outlier count in summary\\n\\n### Regression Detection\\n\\n**Thresholds (configurable via env):**\\n- Time regression: >20% slower than baseline (BR_BENCH_TIME_THRESHOLD=0.20)\\n- Memory regression: >50% higher RSS than baseline (BR_BENCH_MEM_THRESHOLD=0.50)\\n- CI threshold: stricter 10% for time (BR_CI=1 mode)\\n\\n**Comparison:**\\n- Compare against stored baseline.json\\n- Report: PASS (within threshold), WARN (5-20% regression), FAIL (>20% regression)\\n- Generate trend chart data for historical analysis\\n\\n### Baseline Storage\\n\\n**Format:**\\n```json\\n{\\n  \\\"version\\\": \\\"1.0\\\",\\n  \\\"generated_at\\\": \\\"2026-01-20T12:00:00Z\\\",\\n  \\\"br_version\\\": \\\"0.9.5\\\",\\n  \\\"br_commit\\\": \\\"abc1234\\\",\\n  \\\"baselines\\\": {\\n    \\\"list_small\\\": {\\\"p50_ms\\\": 45, \\\"p95_ms\\\": 62, \\\"rss_mb\\\": 12},\\n    \\\"list_medium\\\": {\\\"p50_ms\\\": 120, \\\"p95_ms\\\": 180, \\\"rss_mb\\\": 45},\\n    ...\\n  }\\n}\\n```\\n\\n**Location:**\\n- benchmarks/baseline.json (committed to repo)\\n- Update via: `cargo bench --features baseline-update`\\n\\n## Acceptance Criteria\\n- [ ] Baseline metrics established for all command groups\\n- [ ] Regression detection flags >20% time increase\\n- [ ] Summary table shows pass/warn/fail status per metric\\n- [ ] CI mode uses stricter thresholds\\n- [ ] Historical trend data exportable\\n\\n## Test Coverage (tests/bench_baselines.rs)\\n- baseline_generation: verify baseline.json created with correct schema\\n- regression_detection_pass: verify no alert when within threshold\\n- regression_detection_warn: verify warning at 10-20% regression\\n- regression_detection_fail: verify failure at >20% regression\\n- threshold_override: verify BR_BENCH_*_THRESHOLD env vars work\\n- ci_mode_thresholds: verify stricter thresholds when BR_CI=1\\n- outlier_filtering: verify IQR outlier removal\\n\\n## Output Format\\n```\\nBenchmark Results (br v0.9.5 @ abc1234)\\n\u250c\u2500\u2500\u2500\u2500\u2500\u2500\u2500\u2500\u2500\u2500\u2500\u2500\u2500\u2500\u2500\u2500\u2500\u252c\u2500\u2500\u2500\u2500\u2500\u2500\u2500\u2500\u2500\u2500\u252c\u2500\u2500\u2500\u2500\u2500\u2500\u2500\u2500\u2500\u2500\u252c\u2500\u2500\u2500\u2500\u2500\u2500\u2500\u2500\u2500\u252c\u2500\u2500\u2500\u2500\u2500\u2500\u2500\u2500\u2510\\n\u2502 Command         \u2502 p50 (ms) \u2502 p95 (ms) \u2502 RSS (MB)\u2502 Status \u2502\\n\u251c\u2500\u2500\u2500\u2500\u2500\u2500\u2500\u2500\u2500\u2500\u2500\u2500\u2500\u2500\u2500\u2500\u2500\u253c\u2500\u2500\u2500\u2500\u2500\u2500\u2500\u2500\u2500\u2500\u253c\u2500\u2500\u2500\u2500\u2500\u2500\u2500\u2500\u2500\u2500\u253c\u2500\u2500\u2500\u2500\u2500\u2500\u2500\u2500\u2500\u253c\u2500\u2500\u2500\u2500\u2500\u2500\u2500\u2500\u2524\\n\u2502 list (small)    \u2502 42       \u2502 58       \u2502 11      \u2502 \u2713 PASS \u2502\\n\u2502 list (medium)   \u2502 135 (+12%)\u2502 195     \u2502 48      \u2502 \u26a0 WARN \u2502\\n\u2502 list (large)    \u2502 890 (+25%)\u2502 1200    \u2502 180     \u2502 \u2717 FAIL \u2502\\n\u2514\u2500\u2500\u2500\u2500\u2500\u2500\u2500\u2500\u2500\u2500\u2500\u2500\u2500\u2500\u2500\u2500\u2500\u2534\u2500\u2500\u2500\u2500\u2500\u2500\u2500\u2500\u2500\u2500\u2534\u2500\u2500\u2500\u2500\u2500\u2500\u2500\u2500\u2500\u2500\u2534\u2500\u2500\u2500\u2500\u2500\u2500\u2500\u2500\u2500\u2534\u2500\u2500\u2500\u2500\u2500\u2500\u2500\u2500\u2518\\n```\\n\\n## Logging Requirements\\n- [BENCH] Running list (medium) - run 1/10\\n- [BENCH] Run 1: 132ms, RSS 45MB\\n- [BENCH] Outlier detected: 892ms (>IQR, discarded)\\n- [BASELINE] list (medium): p50=120ms \u2192 135ms (+12.5%) \u26a0 WARN\",\"status\":\"closed\",\"priority\":3,\"issue_type\":\"task\",\"assignee\":\"DarkFinch\",\"owner\":\"jeff141421@gmail.com\",\"created_at\":\"2026-01-18T03:49:26.914745761Z\",\"created_by\":\"Dicklesworthstone\",\"updated_at\":\"2026-01-21T00:54:57.980077004Z\",\"closed_at\":\"2026-01-21T00:53:04.908824718Z\",\"close_reason\":\"Completed\",\"source_repo\":\".\",\"compaction_level\":0,\"original_size\":0,\"dependencies\":[{\"issue_id\":\"beads_rust-kvfz\",\"depends_on_id\":\"beads_rust-ag35\",\"type\":\"parent-child\",\"created_at\":\"2026-03-08T22:47:30Z\",\"created_by\":\"import\",\"metadata\":\"{}\",\"thread_id\":\"\"},{\"issue_id\":\"beads_rust-kvfz\",\"depends_on_id\":\"beads_rust-owu6\",\"type\":\"blocks\",\"created_at\":\"2026-03-08T22:47:30Z\",\"created_by\":\"import\",\"metadata\":\"{}\",\"thread_id\":\"\"},{\"issue_id\":\"beads_rust-kvfz\",\"depends_on_id\":\"beads_rust-u8yr\",\"type\":\"blocks\",\"created_at\":\"2026-03-08T22:47:30Z\",\"created_by\":\"import\",\"metadata\":\"{}\",\"thread_id\":\"\"}],\"comments\":[{\"id\":158,\"issue_id\":\"beads_rust-kvfz\",\"author\":\"Dicklesworthstone\",\"text\":\"Implemented benchmark regression harness using Criterion baselines and a Python analyzer script. 'scripts/bench_regression.sh' handles baseline management and comparison. 'benches/storage_perf.rs' now respects BENCH_NOISE_THRESHOLD and BENCH_SIGNIFICANCE_LEVEL env vars.\",\"created_at\":\"2026-01-21T00:53:01Z\"}]}"
    },
    {
      "sha": "68cb672fac6f17d17e0cc557463e6f89a16013ed",
      "filename": "src/cli/commands/dep.rs",
      "status": "modified",
      "additions": 63,
      "deletions": 0,
      "changes": 63,
      "blob_url": "https://github.com/Dicklesworthstone/beads_rust/blob/4f55a3ede5de73e24eaf53f88044029c293c0102/src%2Fcli%2Fcommands%2Fdep.rs",
      "raw_url": "https://github.com/Dicklesworthstone/beads_rust/raw/4f55a3ede5de73e24eaf53f88044029c293c0102/src%2Fcli%2Fcommands%2Fdep.rs",
      "contents_url": "https://api.github.com/repos/Dicklesworthstone/beads_rust/contents/src%2Fcli%2Fcommands%2Fdep.rs?ref=4f55a3ede5de73e24eaf53f88044029c293c0102",
      "patch": "@@ -548,6 +548,8 @@ fn dep_list(\n         OutputFormat::Text | OutputFormat::Csv => {}\n     }\n \n+    sort_dep_list_items_for_human(&mut items);\n+\n     if items.is_empty() {\n         let direction_str = match args.direction {\n             DepDirection::Down => \"dependencies\",\n@@ -745,6 +747,16 @@ fn apply_external_dep_list_metadata(\n     }\n }\n \n+fn sort_dep_list_items_for_human(items: &mut [DepListItem]) {\n+    items.sort_by(|left, right| {\n+        left.priority\n+            .cmp(&right.priority)\n+            .then_with(|| left.issue_id.cmp(&right.issue_id))\n+            .then_with(|| left.depends_on_id.cmp(&right.depends_on_id))\n+            .then_with(|| left.dep_type.cmp(&right.dep_type))\n+    });\n+}\n+\n fn resolve_dep_tree_node_metadata(\n     storage: &SqliteStorage,\n     root_id: &str,\n@@ -1212,6 +1224,17 @@ mod tests {\n         }\n     }\n \n+    fn test_dep_list_item(issue_id: &str, depends_on_id: &str, priority: i32) -> DepListItem {\n+        DepListItem {\n+            issue_id: issue_id.to_string(),\n+            depends_on_id: depends_on_id.to_string(),\n+            dep_type: \"blocks\".to_string(),\n+            title: depends_on_id.to_string(),\n+            status: \"open\".to_string(),\n+            priority,\n+        }\n+    }\n+\n     #[test]\n     fn test_dependency_type_parsing() {\n         init_test_logging();\n@@ -1493,6 +1516,46 @@ mod tests {\n         info!(\"test_dep_list_item_json: assertions passed\");\n     }\n \n+    #[test]\n+    fn test_sort_dep_list_items_for_human_orders_by_priority() {\n+        init_test_logging();\n+        info!(\"test_sort_dep_list_items_for_human_orders_by_priority: starting\");\n+        let mut items = vec![\n+            test_dep_list_item(\"bd-root\", \"bd-low\", 4),\n+            test_dep_list_item(\"bd-root\", \"bd-critical\", 0),\n+            test_dep_list_item(\"bd-root\", \"bd-medium\", 2),\n+        ];\n+\n+        sort_dep_list_items_for_human(&mut items);\n+\n+        let sorted_ids: Vec<_> = items\n+            .iter()\n+            .map(|item| item.depends_on_id.as_str())\n+            .collect();\n+        assert_eq!(sorted_ids, [\"bd-critical\", \"bd-medium\", \"bd-low\"]);\n+        info!(\"test_sort_dep_list_items_for_human_orders_by_priority: assertions passed\");\n+    }\n+\n+    #[test]\n+    fn test_sort_dep_list_items_for_human_uses_ids_as_tiebreakers() {\n+        init_test_logging();\n+        info!(\"test_sort_dep_list_items_for_human_uses_ids_as_tiebreakers: starting\");\n+        let mut items = vec![\n+            test_dep_list_item(\"bd-root\", \"bd-b\", 1),\n+            test_dep_list_item(\"bd-root\", \"bd-a\", 1),\n+            test_dep_list_item(\"bd-root\", \"bd-c\", 1),\n+        ];\n+\n+        sort_dep_list_items_for_human(&mut items);\n+\n+        let sorted_ids: Vec<_> = items\n+            .iter()\n+            .map(|item| item.depends_on_id.as_str())\n+            .collect();\n+        assert_eq!(sorted_ids, [\"bd-a\", \"bd-b\", \"bd-c\"]);\n+        info!(\"test_sort_dep_list_items_for_human_uses_ids_as_tiebreakers: assertions passed\");\n+    }\n+\n     #[test]\n     fn test_cycles_result_json() {\n         init_test_logging();"
    }
  ]
}
