{
  "message": "feat(fnp-python): expand linalg submodule (diagonal/outer/trace/vector_norm/LinAlgError)\n\nExtends fnp_python.linalg to cover the remaining Array-API + legacy\nnumpy.linalg surface missed in f4af92f:\n\n- diagonal / outer / trace \u2014 already exposed at top level, now\n  aliased under fnp_python.linalg.<name> to match numpy.linalg.\n\n- vector_norm \u2014 Array-API-only (no top-level equivalent in numpy). Added\n  linalg_vector_norm #[pyfunction] that lazy-loads numpy.linalg.vector_norm\n  at call time (same pattern as linalg_cross) since it's not at top.\n\n- LinAlgError \u2014 numpy.linalg's exception type. Re-exports it at\n  fnp_python.linalg.LinAlgError so user code catching\n  'except fnp_python.linalg.LinAlgError' works identically to\n  'except numpy.linalg.LinAlgError'.\n\nProbe extends k74v_5_nested_submodules_expose_numpy_native_names to\nassert all 5 new attributes resolve. Workspace: 3743 passed under\nparallel cargo test.",
  "files": [
    {
      "sha": "1bb1ad00b1389fd9ae40601076a59761623c1087",
      "filename": "crates/fnp-python/src/lib.rs",
      "status": "modified",
      "additions": 25,
      "deletions": 2,
      "changes": 27,
      "blob_url": "https://github.com/Dicklesworthstone/franken_numpy/blob/52f0bda045effbb0f51710577d808c052b6ada79/crates%2Ffnp-python%2Fsrc%2Flib.rs",
      "raw_url": "https://github.com/Dicklesworthstone/franken_numpy/raw/52f0bda045effbb0f51710577d808c052b6ada79/crates%2Ffnp-python%2Fsrc%2Flib.rs",
      "contents_url": "https://api.github.com/repos/Dicklesworthstone/franken_numpy/contents/crates%2Ffnp-python%2Fsrc%2Flib.rs?ref=52f0bda045effbb0f51710577d808c052b6ada79",
      "patch": "@@ -13557,6 +13557,15 @@ fn linalg_cross(py: Python<'_>, args: &Bound<'_, PyTuple>, kwargs: Option<&Bound\n     Ok(np_linalg.getattr(\"cross\")?.call(args, kwargs)?.unbind())\n }\n \n+// linalg.vector_norm passthrough \u2014 Array-API spec name, only exists\n+// under numpy.linalg (not at top level).\n+#[pyfunction]\n+#[pyo3(signature = (*args, **kwargs))]\n+fn linalg_vector_norm(py: Python<'_>, args: &Bound<'_, PyTuple>, kwargs: Option<&Bound<'_, PyDict>>) -> PyResult<Py<PyAny>> {\n+    let np_linalg = py.import(\"numpy.linalg\")?;\n+    Ok(np_linalg.getattr(\"vector_norm\")?.call(args, kwargs)?.unbind())\n+}\n+\n // ---------------------------------------------------------------------------\n // Reality-check (k74v.2) \u2014 ~45 core numpy function passthrough wrappers.\n //\n@@ -14506,6 +14515,9 @@ fn fnp_python(m: &Bound<'_, PyModule>) -> PyResult<()> {\n             (\"eigvalsh\", \"eigvalsh\"),\n             (\"tensordot\", \"tensordot\"),\n             (\"matmul\", \"matmul\"),\n+            (\"diagonal\", \"diagonal\"),\n+            (\"outer\", \"outer\"),\n+            (\"trace\", \"trace\"),\n         ] {\n             if let Ok(value) = m.getattr(flat_name) {\n                 linalg.add(numpy_name, value)?;\n@@ -14517,10 +14529,20 @@ fn fnp_python(m: &Bound<'_, PyModule>) -> PyResult<()> {\n         // during module init if pyo3 launches its embedded interpreter\n         // before numpy is on sys.path.\n         linalg.add_function(wrap_pyfunction!(linalg_cross, &linalg)?)?;\n-        // Expose it under the numpy-native name by re-setting the\n-        // attribute with the short name.\n         linalg.setattr(\"cross\", linalg.getattr(\"linalg_cross\")?)?;\n         linalg.delattr(\"linalg_cross\")?;\n+        // linalg.vector_norm \u2014 Array-API spec name, only exists under\n+        // numpy.linalg. Register via the same lazy-load pattern.\n+        linalg.add_function(wrap_pyfunction!(linalg_vector_norm, &linalg)?)?;\n+        linalg.setattr(\"vector_norm\", linalg.getattr(\"linalg_vector_norm\")?)?;\n+        linalg.delattr(\"linalg_vector_norm\")?;\n+        // Re-export numpy.linalg.LinAlgError so users catching\n+        // fnp_python.linalg.LinAlgError still catch numpy's exception type.\n+        if let Ok(np_linalg) = py.import(\"numpy.linalg\") {\n+            if let Ok(exc) = np_linalg.getattr(\"LinAlgError\") {\n+                linalg.add(\"LinAlgError\", exc)?;\n+            }\n+        }\n         m.add_submodule(&linalg)?;\n         // Also expose as top-level attribute so `fnp_python.linalg` resolves\n         // via attribute access regardless of import style.\n@@ -15490,6 +15512,7 @@ mod tests {\n                 \"matrix_transpose\", \"pinv\", \"norm\", \"cond\", \"tensorinv\",\n                 \"tensorsolve\", \"multi_dot\", \"det\", \"solve_triangular\",\n                 \"eigh\", \"eigvals\", \"eigvalsh\", \"cross\", \"tensordot\", \"matmul\",\n+                \"diagonal\", \"outer\", \"trace\", \"vector_norm\", \"LinAlgError\",\n             ] {\n                 assert!(\n                     linalg.getattr(name).is_ok(),"
    }
  ]
}
