{
  "message": "\ud83c\udf31 apisix: Proposal: support OpenPolicyAgent for access control (#1584)\n\n* \ud83c\udf31 Add apisix: Proposal: support OpenPolicyAgent for access control mission\n\nSigned-off-by: github-actions[bot] <41898282+github-actions[bot]@users.noreply.github.com>\n\n* \ud83d\udc1b fix: clean up mission content for apisix OPA plugin\n\nReplace raw schema table in step 3 and codeSnippets with actual\nAPISIX OPA plugin configuration example. Clean up resolution summary.\n\nSigned-off-by: Andrew Anderson <andy@clubanderson.com>\n\n---------\n\nSigned-off-by: github-actions[bot] <41898282+github-actions[bot]@users.noreply.github.com>\nSigned-off-by: Andrew Anderson <andy@clubanderson.com>\nCo-authored-by: github-actions[bot] <41898282+github-actions[bot]@users.noreply.github.com>",
  "files": [
    {
      "sha": "07a4da4d884a55e399d5c55b46505d61afd0283b",
      "filename": "solutions/cncf-generated/apisix/apisix-5714-proposal-support-openpolicyagent-for-access-control.json",
      "status": "added",
      "additions": 75,
      "deletions": 0,
      "changes": 75,
      "blob_url": "https://github.com/kubestellar/console-kb/blob/96bfc7f1686d3df61fc154de3f1c3796409ac8b2/solutions%2Fcncf-generated%2Fapisix%2Fapisix-5714-proposal-support-openpolicyagent-for-access-control.json",
      "raw_url": "https://github.com/kubestellar/console-kb/raw/96bfc7f1686d3df61fc154de3f1c3796409ac8b2/solutions%2Fcncf-generated%2Fapisix%2Fapisix-5714-proposal-support-openpolicyagent-for-access-control.json",
      "contents_url": "https://api.github.com/repos/kubestellar/console-kb/contents/solutions%2Fcncf-generated%2Fapisix%2Fapisix-5714-proposal-support-openpolicyagent-for-access-control.json?ref=96bfc7f1686d3df61fc154de3f1c3796409ac8b2",
      "patch": "@@ -0,0 +1,75 @@\n+{\n+  \"version\": \"kc-mission-v1\",\n+  \"name\": \"apisix-5714-proposal-support-openpolicyagent-for-access-control\",\n+  \"missionClass\": \"solution\",\n+  \"author\": \"KubeStellar Bot\",\n+  \"authorGithub\": \"kubestellar\",\n+  \"mission\": {\n+    \"title\": \"apisix: Proposal: support OpenPolicyAgent for access control\",\n+    \"description\": \"Proposal: support OpenPolicyAgent for access control. Requested by 5+ users.\",\n+    \"type\": \"feature\",\n+    \"status\": \"completed\",\n+    \"steps\": [\n+      {\n+        \"title\": \"Check current apisix deployment\",\n+        \"description\": \"Verify your apisix version and configuration:\\n```bash\\nkubectl get pods -n apisix -l app.kubernetes.io/name=apisix\\nhelm list -n apisix 2>/dev/null || echo \\\"Not installed via Helm\\\"\\n```\\nThis feature requires a working apisix installation.\"\n+      },\n+      {\n+        \"title\": \"Review apisix configuration\",\n+        \"description\": \"Inspect the relevant apisix configuration:\\n```bash\\nkubectl get all -n apisix -l app.kubernetes.io/name=apisix\\nkubectl get configmap -n apisix -l app.kubernetes.io/part-of=apisix\\n```\\nOPA is an open source lightweight general-purpose policy engine, which is a full-featured policy engine that can replace the built-in policy module in your software and decouple the service from the policy engine.\"\n+      },\n+      {\n+        \"title\": \"Apply the fix for Proposal: support OpenPolicyAgent for access control\",\n+        \"description\": \"The OPA plugin was implemented in PR apache/apisix#5734. To use it, configure the `opa` plugin on your APISIX route with the policy URI and request/response body handling options.\\n```yaml\\n# Example: Enable OPA plugin on an APISIX route\\ncurl http://127.0.0.1:9180/apisix/admin/routes/1 \\\\\\n  -H 'X-API-KEY: your-api-key' -X PUT -d '\\n{\\n  \\\"uri\\\": \\\"/get\\\",\\n  \\\"plugins\\\": {\\n    \\\"opa\\\": {\\n      \\\"host\\\": \\\"http://opa-service:8181\\\",\\n      \\\"policy\\\": \\\"example/allow\\\",\\n      \\\"with_route\\\": true,\\n      \\\"with_consumer\\\": true\\n    }\\n  },\\n  \\\"upstream\\\": {\\n    \\\"type\\\": \\\"roundrobin\\\",\\n    \\\"nodes\\\": {\\n      \\\"httpbin.org:80\\\": 1\\n    }\\n  }\\n}'\\n```\"\n+      },\n+      {\n+        \"title\": \"Verify the feature works\",\n+        \"description\": \"Test that the new capability is working as expected:\\n```bash\\nkubectl get pods -n apisix -l app.kubernetes.io/name=apisix\\nkubectl get events -n apisix --sort-by='.lastTimestamp' | tail -10\\n```\\nConfirm the feature described in \\\"Proposal: support OpenPolicyAgent for access control\\\" is functioning correctly.\"\n+      }\n+    ],\n+    \"resolution\": {\n+      \"summary\": \"The OPA plugin for access control was added to Apache APISIX via PR #5734. Configure it on routes using the `opa` plugin with `conf.host` pointing to your OPA server and `conf.policy` specifying the policy path.\",\n+      \"codeSnippets\": [\n+        \"# Enable OPA plugin on an APISIX route\\ncurl http://127.0.0.1:9180/apisix/admin/routes/1 \\\\\\n  -H 'X-API-KEY: your-api-key' -X PUT -d '\\n{\\n  \\\"uri\\\": \\\"/get\\\",\\n  \\\"plugins\\\": {\\n    \\\"opa\\\": {\\n      \\\"host\\\": \\\"http://opa-service:8181\\\",\\n      \\\"policy\\\": \\\"example/allow\\\",\\n      \\\"with_route\\\": true,\\n      \\\"with_consumer\\\": true\\n    }\\n  },\\n  \\\"upstream\\\": {\\n    \\\"type\\\": \\\"roundrobin\\\",\\n    \\\"nodes\\\": {\\n      \\\"httpbin.org:80\\\": 1\\n    }\\n  }\\n}' \"\n+      ]\n+    }\n+  },\n+  \"metadata\": {\n+    \"tags\": [\n+      \"apisix\",\n+      \"community\",\n+      \"api-gateway\",\n+      \"feature\"\n+    ],\n+    \"cncfProjects\": [\n+      \"apisix\"\n+    ],\n+    \"targetResourceKinds\": [],\n+    \"difficulty\": \"intermediate\",\n+    \"issueTypes\": [\n+      \"feature\"\n+    ],\n+    \"maturity\": \"community\",\n+    \"sourceUrls\": {\n+      \"issue\": \"https://github.com/apache/apisix/issues/5714\",\n+      \"repo\": \"https://github.com/apache/apisix\",\n+      \"pr\": \"https://github.com/apache/apisix/pull/5734\"\n+    },\n+    \"reactions\": 5,\n+    \"comments\": 19,\n+    \"synthesizedBy\": \"copilot\"\n+  },\n+  \"prerequisites\": {\n+    \"kubernetes\": \">=1.24\",\n+    \"tools\": [\n+      \"kubectl\"\n+    ],\n+    \"description\": \"A running Kubernetes cluster with apisix installed or the issue environment reproducible.\"\n+  },\n+  \"security\": {\n+    \"scannedAt\": \"2026-03-20T06:49:51.100Z\",\n+    \"scannerVersion\": \"cncf-gen-3.0.0\",\n+    \"sanitized\": true,\n+    \"findings\": []\n+  }\n+}"
    }
  ]
}
